Workbook
Name ___INDEX_SHEET___ASAP_Utilities: #REF!
Name ___INDEX_SHEET___ASAP_Utilities: #REF!
Name ___INDEX_SHEET___ASAP_Utilities: #REF!
Name _ftn1: '29. Addl Info to the FS '!#REF!
Name _ftn2: '29. Addl Info to the FS '!#REF!
Name _ftn3: '29. Addl Info to the FS '!#REF!
Name _ftn4: '29. Addl Info to the FS '!#REF!
Name _ftn5: '29. Addl Info to the FS '!#REF!
Name _ftnref5: '29. Addl Info to the FS '!#REF!
Name Contents: #REF!

Sheet Computation

Sheet Disallowances22-23
A4: SUF GROUP 2022 2023
A5: CURRENT LIABILITIES
A6: Group Summary
A7: 1-Apr-22 to 31-Mar-23 | H7: Disallowance | I7: Expense head | J7: Disallowance of
B8: CURRENT LIABILITIES | H8: FY 2022-2023 | J8: FY 2021-2022 | K8: Expense head | L8: Paid On
B9: SUF GROUP 2022 2023
A10: Particulars | B10: 1-Apr-22 to 31-Mar-23
B11: Opening | C11: Transactions | E11: Closing
B12: Balance | C12: Debit | D12: Credit | E12: Balance
A13: DUTIES & TAXES | B13: 47400.36 | C13: 1406505 | D13: 1838487.4 | E13: 384582 | H13: 20400 | I13: Prof Tax - Salary
A14: PROVISIONS | B14: 425500 | C14: 28512139 | D14: 28997639 | E14: 981000 | H14: 90506 | I14: TDS - Salary | J14: 5400 | K14: Salary | L14: 44664
A15: SUNDRY CREDITORS | B15: 259604 | C15: 42094136 | D15: 41764532 | E15: 70000 | H15: 11366 | I15: TDS - Rent | J15: 17327 | K15: Staff TRng - 223, social service - 17085, comp - 19 | L15: 09-04-2022, 13-04-2022
A16: ESI PAYABLE | B16: 57147 | C16: 930496.99 | D16: 1030232 | E16: 156882 | H16: 37880 | I16: TDS- Contractors | J16: 80826 | K16: audit fees - 2500, mohan vs advance - 5k, prof chgs - 2400, fin consul - 10300 | L16: 09-04-2022, 13-04-2022
A17: ESI CO CONTRIBUTION PAYABLE | B17: 46403 | C17: 755635.99 | D17: 836633.99 | E17: 127401 | G17: =SUM(H13:H17) -> 384582 | H17: 224430 | I17: TDS - Professional | J17: 12745 | K17: Rent | L17: 44660
A18: ESI EMPLOYEE CONTRIBUTION PAYABLE | B18: 10744 | C18: 174861 | D18: 193598 | E18: 29481 | G18: =E16 -> 156882 | I18: Salary | J18: 7405 | K18: Salary | L18: 44660
A19: GRANT UNNATI - UNUTILISED | B19: 9296220 | C19: 85266289 | D19: 176340817 | E19: 100370748 | J19: 234000 | K19: Youth training exps (vision fly ) - Op bal 3,96,000 , out of which 234000 is written back | L19: Unpaid / written back
A20: PROVIDENT FUNDS PAYABLE | B20: 262442 | C20: 4862577 | D20: 5405965 | E20: 805830 | G20: =E20 -> 805830 | I20: Salary | J20: 1104 | K20: Comp - grant (tata power extra bill) | L20: Unpaid / written back
A21: REFUNDABLE DEPOSIT | B21: 186900 | C21: 186900 | H21: 95000 | I21: Audit fees | J21: 3500 | K21: FA | L21: 44687
A22: Grand Total | B22: 10440413 | C22: 1.6325904e+08 | D22: 2.5537767e+08 | E22: 102559042 | G22: =H21+H22 -> 819000 | H22: 724000 | I22: Youth training exps only of FY 2022-2023, minus op bal disallowed in FY 2021-2022 | J22: -50000 | K22: Advance to creditors added to application, to be reduced from application of FY 2022-2023 | L22: 44639
G23: 50000 | H23: Advance to creditors added to application in FY 2021-2022, to be reduced from application of FY 2022-2023 | J23: 30000 | K23: Rent | L23: Unpaid / written back
G24: -70000 | H24: Advance to creditors added to application for FY 2022-2023, to be reduced from application of FY 2023-2024 | J24: 135000 | K24: Youth Trng Exps | L24: 44664
J25: 46403 | K25: Salary | L25: 44664
J26: 10744 | K26: Salary | L26: 44664
J27: 148693 | K27: Salary | L27: 06-04-2022, 13-04-2022
J28: 113749 | K28: Salary
H30: =SUM(H13:H29) -> 1203582 | J30: =SUM(J13:J29) -> 796896

Sheet Balance Sheet
A1: SOCIAL FOUNDATION
A2: CIN:
A3: Address:
A4: Balance Sheet as at 31st March, 2025
A7: Particulars | E7: Note No. | F7: As at 31 March, 2025 | G7: As at 31 March, 2024
F8: INR | G8: INR
A9: A | B9: EQUITY AND LIABILITIES
A11: 1 | B11: Shareholders’ funds
B12: (a) Share capital | E12: 1
A14: 2 | B14: Reserves and Earmarked Funds | E14: 2
A16: 3 | B16: Non-current liabilities
A18: 4 | B18: Current liabilities | E18: 3
D20: TOTAL | F20: =SUM(F12:F19) -> 0 | G20: =SUM(G12:G19) -> 0
A22: B | B22: ASSETS
A24: 1 | B24: Fixed Assets | E24: 13&13A
A26: 2 | B26: Non-current assets | E26: 4
A28: 3 | B28: Current assets | E28: 5
D30: TOTAL | F30: =SUM(F24:F29) -> 0 | G30: =SUM(G24:G29) -> 0
B31: See accompanying notes forming part of the financial statements | F31: =F20-F30 -> 0
A32: As per our report of even date:
A33: For Auditor | E33: For and on behalf of the Board of Directors
A34: Chartered Accountants | E34: Social Foundation
A35: ICAI FR No:
A40: Partner | E40: Director | G40: Director
A41: ICAI MRN: | E41: DIN: | G41: DIN:
A42: UDIN:
A43: Place :
A44: Date :

Sheet Income & Expenditure
A1: SOCIAL FOUNDATION
A2: CIN:
A3: Address:
A4: Statement of Income and Expenditure for the year ended 31st March 2025
A6: Particulars | C6: Note No. | D6: For the year ended 31 March, 2025 | E6: For the year ended 31 March, 2024
D7: INR | E7: INR
A8: A | B8: CONTINUING OPERATIONS
A10: 1 | B10: Donations & Grants Received | C10: 6
A11: 2 | B11: Other income | C11: 7
A13: 3 | B13: Total revenue (1+2) | D13: =SUM(D10:D12) -> 0 | E13: =SUM(E10:E12) -> 0
A14: 4 | B14: Expenses
B15: (a) Salaries, Allowances & Benefits | C15: 8
B16: (b) Program Expenses | C16: 9
B17: (c) General & Admin Expenses | C17: 10
B18: ( d ) Depreciation | C18: 13A
B20: Total expenses (4) | D20: =SUM(D15:D19) -> 0 | E20: =SUM(E15:E19) -> 0
A22: 5 | B22: Excess of Income / (Expenditure) before extraordinary items and tax | D22: =+D13-D20 -> 0 | E22: =+E13-E20 -> 0
A23: 6 | B23: Exceptional items | D23: 0 | E23: 0
A24: 7 | B24: Excess of Income / (Expenditure) before extraordinary items and tax (5 + 6) | D24: =+D23+D22 -> 0 | E24: =+E23+E22 -> 0
A25: 8 | B25: Prior Period Adjustments for Depreciation | E25: 0
A26: 9 | B26: Excess of Income / (Expenditure) before tax (7 + 8) | D26: =+D25+D24 -> 0 | E26: =+E25+E24 -> 0
A27: 10 | B27: Tax expense:
B28: Income Tax | D28: 0 | E28: 0
A29: 11 | B29: Excess of Income / (Expenditure) from continuing operations (9 +10) | D29: =+D28+D26 -> 0 | E29: =+E28+E26 -> 0
A30: B | B30: DISCONTINUING OPERATIONS
A31: 12 | B31: Excess of Income / (Expenditure) from discontinuing operations (before tax) | D31: 0 | E31: 0
A32: 13 | B32: Excess of Income / (Expenditure) from discontinuing operations (12.i + 12.ii + 12.iii) | D32: =+D31 -> 0 | E32: =+E31 -> 0
A33: C | B33: TOTAL OPERATIONS
A34: 14 | B34: Excess of Income / (Expenditure) for the year (11 + 13) | D34: =+D29+D32 -> 0 | E34: =+E29+E32 -> 0
A36: 15.i | B36: Earnings per share (of RS. 10/- each):
B37: (a) Basic
B38: (i) Continuing operations | D38: =+D29/10000 -> 0 | E38: =+E29/10000 -> 0
B39: (ii) Total operations | D39: =+D34/10000 -> 0 | E39: =+E34/10000 -> 0
B40: (b) Diluted
B41: (i) Continuing operations | D41: =+D38 -> 0 | E41: =+E38 -> 0
B42: (ii) Total operations | D42: =+D39 -> 0 | E42: =+E39 -> 0
A43: 15.ii | B43: Earnings per share (excluding extraordinary items) (of Rs. 10/- each):
B44: (a) Basic
B45: (i) Continuing operations | D45: =+D38 -> 0 | E45: =+E38 -> 0
B46: (ii) Total operations | D46: =+D39 -> 0 | E46: =+E39 -> 0
B47: (b) Diluted
B48: (i) Continuing operations | D48: =+D41 -> 0 | E48: =+E41 -> 0
B49: (ii) Total operations | D49: =+D42 -> 0 | E49: =+E42 -> 0
B50: See accompanying notes forming part of the financial statements
A51: As per our report of even date:
A52: For Auditor | C52: For and on behalf of the Board of Directors
A53: Chartered Accountants | C53: Social Foundation
A54: ICAI FR No:
A59: Partner | C59: Director | E59: Director
A60: ICAI MRN: | C60: DIN: | E60: DIN:
A61: UDIN:
A62: Place :
A63: Date :

Sheet Fund Based I&E
A1: SOCIAL FOUNDATION
A2: CIN:
A3: Address:
A4: Fund Based Statement of Income and Expenditure for the year ended 31st March 2025
A7: Particulars | B7: For the year ended 31st March, 2025 (INR)
B8: Restricted Funds | C8: Unrestricted Funds | D8: Total
A9: Income
A10: Donations & Grants | D10: ='Income & Expenditure'!D10 -> 0
A11: Other Income | B11: 0 | C11: =+D11 -> 0 | D11: ='Income & Expenditure'!D11 -> 0
A12: Total Income | B12: =SUM(B10:B11) -> 0 | C12: =SUM(C10:C11) -> 0 | D12: =SUM(D10:D11) -> 0
A14: Expenditure | E14: Adobe | F14: Broadridge | G14: Cardinal Health | H14: Compass India Support Services Pvt Ltd | I14: Deloitte Foundation | J14: E2E Rail | K14: Essel Social Welfare Foundation | L14: Exxon Mobil | M14: Finastra | N14: GE BE Pvt Ltd | O14: GE India Industrial Pvt Ltd | P14: Infosys Foundation | Q14: Intertrust Videos India | R14: Intek Tapes | S14: Microchip Tech (I) Pvt Ltd | T14: MUFG Bank Ltd | U14: NASDAQ | V14: Nextwealth | W14: Omega Healthcare Management Services | X14: Rubrik | Y14: Societe Generale Global Solutions Centre Pvt Ltd | Z14: SSE-ZCZP | AA14: Tata Capital Financial Services Ltd | AB14: Tata Hitachi | AC14: Tata Power Community Development Trust | AD14: Tata Power Delhi Distribution Ltd | AE14: The Boeing Company Ltd | AF14: Unisys India Pvt Ltd | AG14: Total
A15: Salaries, Allowances & Benefits | E15: 1158654 | F15: 6205000 | G15: 20093 | H15: 2215437 | I15: 2564023 | K15: 1045491 | L15: 11287238 | M15: 1092220 | N15: 137783 | O15: 3342149 | P15: 71874192 | Q15: 405549 | R15: 269280 | S15: 1455918 | T15: 7585265 | U15: 157877 | V15: 1315168 | W15: 4085278 | X15: 994258 | Y15: 3636654 | Z15: =12293451+185806+548295+513468.88 -> 13541021 | AB15: 400000 | AC15: 458251 | AD15: 2100000 | AE15: 3194354 | AF15: =260476+323200 -> 583676 | AG15: =SUM(E15:AF15) -> 1.4112483e+08
A16: Program Expenses
A17: Asset Purchases From Restricted Funds | AE17: 1032818 | AG17: =SUM(E17:AF17) -> 1032818
A18: Bank Charges | K18: 125 | Z18: 50000 | AG18: =SUM(E18:AF18) -> 50125
A19: Catering & Pantry Expenses | K19: 9670 | W19: 49773 | Y19: 2092750 | AF19: 163947 | AG19: =SUM(E19:AF19) -> 2316140
A20: Centre Setup & Shifting Expenses | W20: 109210 | AE20: 630323.2 | AG20: =SUM(E20:AF20) -> 739533.2
A21: Computer Maintenance | K21: 475 | W21: 29536 | Z21: =402+9305 -> 9707 | AG21: =SUM(E21:AF21) -> 39718
A22: Electricity & Water | W22: 106768 | AF22: 16373 | AG22: =SUM(E22:AF22) -> 123141
A23: Housekeeping, Repairs & Maintenance | K23: 44878 | W23: =39099+2374 -> 41473 | AD23: 50000 | AE23: 748334.94 | AG23: =SUM(E23:AF23) -> 884685.94
A24: Interest on Unutilised Grants | AG24: =SUM(E24:AF24) -> 0
A25: Medical Expenses | AG25: =SUM(E25:AF25) -> 0
A26: Membership Fees | T26: 309400 | AG26: =SUM(E26:AF26) -> 309400
A27: Miscelleneous Expenses | AG27: =SUM(E27:AF27) -> 0
A28: Monitoring & Supervision Cost | AG28: =SUM(E28:AF28) -> 0
A29: Outreach Expenses | K29: 212350 | O29: 1050000 | P29: 982172 | Q29: 335984 | T29: 77232 | U29: 333719 | W29: 336287 | Y29: 499994 | Z29: =175008.56+1673 -> 176681.56 | AC29: 76186 | AF29: 14408 | AG29: =SUM(E29:AF29) -> 4095013.6
A30: Postage, Telephone & Internet Expenses | K30: 15395 | P30: 27315 | W30: 58534 | Z30: =4867.36 -> 4867.36 | AG30: =SUM(E30:AF30) -> 106111.36
A31: Printing and stationery | K31: 8527 | AG31: =SUM(E31:AF31) -> 8527
A32: Rent | G32: 1070 | I32: 40647 | N32: 7335 | O32: 4431 | P32: 1549959 | Q32: 6724 | T32: 1178630.1 | U32: 8404 | W32: =916920+230429 -> 1147349 | Y32: 61123 | Z32: 276179.77 | AE32: 22921 | AF32: 136000 | AG32: =SUM(E32:AF32) -> 4440772.9
A33: Software Subscription | P33: 327541 | W33: 18522 | Z33: 58362.92 | AE33: 397382.6 | AG33: =SUM(E33:AF33) -> 801808.52
A34: Staff Training, Recruitment & HR Expenses | E34: 360150 | G34: 38837 | I34: 295689 | K34: 41284 | M34: 339500 | O34: 668850 | P34: =12871467+2263469 -> 15134936 | Q34: 40448 | S34: 452550 | V34: 408800 | W34: =4022+404529 -> 408551 | X34: 309050 | Y34: 666275.62 | Z34: =2293505.38+403316.72 -> 2696822.1 | AE34: 292709.26 | AG34: =SUM(E34:AF34) -> 22154452
A35: Training Materials & Other Expenses | P35: 177541 | W35: 65584 | Z35: 22330.29 | AF35: 6354 | AG35: =SUM(E35:AF35) -> 271809.29
A36: Training Partner Expenses | I36: 2099641 | N36: 296882 | O36: 841088 | Q36: 11295 | R36: 230720 | T36: 7880739 | W36: 708921 | AF36: 1050000 | AG36: =SUM(E36:AF36) -> 13119286
A37: Training Software | H37: 148313 | K37: 5387 | P37: 3768706 | W37: 24610 | Y37: 107224.38 | Z37: 671527.71 | AF37: 2998 | AG37: =SUM(E37:AF37) -> 4728766.1
A38: Travelling and conveyance | K38: =200+327000 -> 327200 | P38: 1908860 | Z38: =340130.7+16297-0.29 -> 356427.41 | AF38: 7782 | AG38: =SUM(E38:AF38) -> 2600269.4
A39: HO Cost Allocation | E39: 70138 | J39: 34728.5 | K39: 22185 | L39: 430333 | M39: 68280 | O39: 193482 | P39: 3077105 | S39: 91532 | V39: 76032 | X39: 56692 | Y39: 135979 | AA39: 75000 | AF39: 18462 | AG39: =SUM(E39:AF39) -> 4349948.5
A40: Social Service Project Expenses | J40: 620271.5 | L40: 5252429 | AA40: 1500000 | AG40: =SUM(E40:AF40) -> 7372700.5
A41: General Expenses | AG41: =SUM(E41:AF41) -> 0
A42: Remuneration to Auditors: | AG42: =SUM(E42:AF42) -> 0
A43: (i) Audit Fees | AG43: =SUM(E43:AF43) -> 0
A44: (ii) Other Services | AG44: =SUM(E44:AF44) -> 0
A45: Commission | AG45: =SUM(E45:AF45) -> 0
A46: Legal Charges | AG46: =SUM(E46:AF46) -> 0
A47: Loss on sale / discarding of asset | AG47: =SUM(E47:AF47) -> 0
A48: Miscelleneous Expenses | AG48: =SUM(E48:AF48) -> 0
A49: Penalty on premature FD withdrawal | AG49: =SUM(E49:AF49) -> 0
A50: Professional Charges | Z50: 59000 | AG50: =SUM(E50:AF50) -> 59000
A51: Rates & Taxes | Z51: 77073 | AG51: =SUM(E51:AF51) -> 77073
A52: Sundry Balances w/off | AG52: =SUM(E52:AF52) -> 0
A53: Depreciation | AG53: =SUM(E53:AF53) -> 0
AG54: =SUM(E54:AF54) -> 0
A55: Total Expenses | B55: =SUM(B15:B54) -> 0 | C55: =SUM(C15:C54) -> 0 | D55: =SUM(D15:D54) -> 0 | E55: =SUM(E15:E54) -> 1588942 | F55: =SUM(F15:F54) -> 6205000 | G55: =SUM(G15:G54) -> 60000 | H55: =SUM(H15:H54) -> 2363750 | I55: =SUM(I15:I54) -> 5000000 | ... AH55: =SUM(AH15:AH54) -> 0
E56: ='Note 12 Restricted Fund Movmnt'!$G8 -> 0 | F56: ='Note 12 Restricted Fund Movmnt'!$G10 -> 0 | G56: ='Note 12 Restricted Fund Movmnt'!#REF! -> #REF! | H56: ='Note 12 Restricted Fund Movmnt'!#REF! -> #REF! | I56: ='Note 12 Restricted Fund Movmnt'!#REF! -> #REF! | J56: ='Note 12 Restricted Fund Movmnt'!#REF! -> #REF! | K56: ='Note 12 Restricted Fund Movmnt'!#REF! -> #REF! | L56: ='Note 12 Restricted Fund Movmnt'!#REF! -> #REF! | M56: ='Note 12 Restricted Fund Movmnt'!#REF! -> #REF! | N56: ='Note 12 Restricted Fund Movmnt'!#REF! -> #REF! | ... AE56: ='Note 12 Restricted Fund Movmnt'!#REF! -> #REF! | AF56: ='Note 12 Restricted Fund Movmnt'!$G12 -> 0 | AG56: =SUM(E56:AF56) -> #REF!
A57: Net Income / (Expenditure) | B57: =B12-B55 -> 0 | C57: =C12-C55 -> 0 | D57: =D12-D55 -> 0 | E57: =E55-E56 -> 1588942 | F57: =F55-F56 -> 6205000 | G57: =G55-G56 -> #REF! | H57: =H55-H56 -> #REF! | I57: =I55-I56 -> #REF! | J57: =J55-J56 -> #REF! | K57: =K55-K56 -> #REF! | L57: =L55-L56 -> #REF! | ... AF57: =AF55-AF56 -> 2000000
A58: See accompanying notes forming part of the financial statements
A59: As per our report of even date:
A60: For Auditor | B60: For and on behalf of the Board of Directors
A61: Chartered Accountants | B61: Social Foundation
A62: ICAI FR No:
A67: Partner | B67: Director | D67: Director
A68: ICAI MRN: | B68: DIN: | D68: DIN:
A69: UDIN:
A70: Place :
A71: Date :

Sheet Note 1 Share Capital
A1: SOCIAL FOUNDATION
A2: Notes forming part of the financial statements
A4: Note 1 Share Capital
A6: Particulars | B6: As at 31 March, 2025 | D6: As at 31 March, 2024
B7: Number of shares | C7: INR | D7: Number of shares | E7: INR
A8: (a) Authorised
A9: Equity shares of INR. 10 each with voting rights
A11: (b) Issued
A12: Equity shares of INR. 10 each with voting rights
A14: (c) Subscribed and fully paid up
A15: Equity shares of INR. 10 each with voting rights
A18: Total | B18: =+B15 -> 0 | C18: =+C15 -> 0 | D18: =+D15 -> 0 | E18: =+E15 -> 0
A20: Notes:
A21: (i) Reconciliation of the number of shares and amount outstanding at the beginning and at the end of the reporting period:
A22: Particulars | B22: Opening Balance | C22: Fresh issue | D22: Closing Balance
A23: Equity shares Subscibed & Fully paid up with voting rights
A25: Year ended 31 March, 2025
A26: - Number of shares
A27: - Amount (INR.)
A29: Year ended 31 March, 2024
A30: - Number of shares
A31: - Amount (INR.)
A33: (ii) Details of shares held by each shareholder holding more than 5% shares:
A34: Class of shares / Name of shareholder | B34: As at 31 March, 2025 | D34: As at 31 March, 2024
B35: Number of shares held | C35: % holding in that class of shares | D35: Number of shares held | E35: % holding in that class of shares
A36: Equity shares with voting rights

Sheet Notes 2 to 11
A1: SOCIAL FOUNDATION
A2: Notes forming part of the financial statements
A4: Particulars | B4: As at 31 March, 2025 | C4: As at 31 March, 2024
B5: INR | C5: INR
A7: Note 2 Reserves and surplus
A8: ( a ) Surplus / (Deficit) in Statement of Income & Expenditure
A9: Opening balance
A10: Add: Surplus / (Deficit) for the year
A11: Closing General Fund Balance | B11: =SUM(B9:B10) -> 0 | C11: =SUM(C9:C10) -> 0
A13: (b) Corpus Fund
A14: Opening Balance
A15: Add: Additions during the year
A16: Less: Withdrawn during the year
A17: Closing Corpus Fund Balance | B17: =B14+B15-B16 -> 0 | C17: =C14+C15-C16 -> 0
A19: ( c ) Deffered Grant for Fixed Assets
A21: Total Reserves and Surplus | B21: =B11+B17+B19 -> 0 | C21: =C11+C17+C19 -> 0
A24: Note 3 Current liabilities
A25: (j) Other payables
A26: (i) Audit Fee & other expenses
A27: (ii) Refundable Deposits
A28: (ii) Restricted Fund Balance (Note 12)
A29: (iii) Statutory remittances (Contributions to PF and ESIC, Withholding Taxes, GST etc.)
A30: (iv) Sundry Creditors, Provisions & Other Payables
A32: Total Current Liabilities | B32: =SUM(B26:B31) -> 0 | C32: =SUM(C26:C31) -> 0
A35: Note 4 Non-Current Assets
A36: (a) Fixed Deposits (Scheduled Banks) with maturity > 1 year
A38: Total Non Current Assets | B38: =SUM(B36) -> 0 | C38: =SUM(C36) -> 0
A52: Note 5 Current Assets
A53: (A) Cash and cash equivalents
A54: (a) Cash on hand | B54: =#REF! -> #REF! | C54: 0
A55: (b) Savings accounts (Scheduled Banks) | B55: =SUM(#REF!)-SUM(#REF!) -> #REF! | C55: 20887598
A56: (c) Fixed Deposits (Scheduled Banks) with maturity < 3 months | B56: =#REF!+#REF!-#REF!-#REF!+#REF!+#REF!-#REF!-#REF!-B63-B36 -> #REF! | C56: 81988332
A57: Total (A) | B57: =SUM(B54:B56) -> #REF! | C57: =SUM(C54:C56) -> 1.0287593e+08
A58: (B) Short-term loans and advances, Deposits etc
A59: (a) Balances with government authorities
A60: (i) TDS receivable, Input taxes etc | B60: =SUM(#REF!)-SUM(#REF!) -> #REF! | C60: 1875030.6
A61: (b) Balances with others
A62: (i) Advance to creditors | B62: =#REF!-#REF! -> #REF! | C62: 55000
A63: (ii) Fixed Deposits (Scheduled Banks) with maturity > 3 months and < 12 months | B63: =#REF! -> #REF! | C63: 143915514
A64: (iii) Rent Deposits | B64: =#REF!-#REF! -> #REF! | C64: 478000
A65: (iv) Staff Advance | B65: =SUM(#REF!)-SUM(#REF!) -> #REF! | C65: 220284
A66: Total (B) | B66: =SUM(B60:B65) -> #REF! | C66: =SUM(C60:C65) -> 1.4654383e+08
A67: (c) Other Amounts Receivable | B67: =#REF!+#REF!-#REF!-#REF!+#REF!-#REF! -> #REF! | C67: 0
A69: Total Current Assets (A+B) | B69: =B57+B66+B67 -> #REF! | C69: =C57+C66+C67 -> 2.4941976e+08
A72: Note 6 Donations & Grants
A73: Grants - CSR | B73: =#REF! -> #REF! | C73: 76438662
A74: Grants - Others | B74: =#REF! -> #REF! | C74: 116367266
A75: Donations | B75: =#REF! -> #REF! | C75: 22851045
A76: Donations - Anonymous | B76: =#REF! -> #REF! | C76: 10975
A77: Total Donations & Grants | B77: =SUM(B73:B76) -> #REF! | C77: =SUM(C73:C76) -> 2.1566795e+08
A80: Note 7 Other income
A81: ( a ) Interest on SB & FD Accounts (Note 25) | B81: =#REF!+#REF!-#REF!-#REF! -> #REF! | C81: 12151770
A82: (b) Interest on Income Tax Refund | B82: =#REF!-#REF! -> #REF! | C82: 0
A83: ( c ) Miscelleneous Receipts | B83: =#REF!-#REF! -> #REF! | C83: 374883
A84: (d) Program Income
A85: 1. Placement Fees | B85: =#REF!-#REF! -> #REF! | C85: 105559
A86: 2. Youth Training Fee | B86: =#REF!-#REF! -> #REF! | C86: 4694100
A87: 3. Other Training Fees | B87: =#REF!-#REF! -> #REF! | C87: 0
A88: Total Other Income | B88: =SUM(B81:B87) -> #REF! | C88: =SUM(C81:C87) -> 17326312
A91: Note 8 Salaries, Allowances & Benefits
A93: Salaries, Allowances, Consultant Fees | B93: =SUM(#REF!)-SUM(#REF!)-SUM(B94:B96) -> #REF! | C93: 1.0995638e+08
A94: Incentives | B94: =#REF!+#REF!+#REF! -> #REF! | C94: 23224578
A95: PF & ESIC Contributions | B95: =#REF!+#REF!+#REF!+SUM(#REF!)-SUM(#REF!)-#REF!-#REF!-#REF!+#REF!-#REF!+#REF!-#REF!+#REF!+#REF!-#REF!-#REF!+#REF!-#REF! -> #REF! | C95: 9750580.3
A96: Gratuity | B96: =#REF!+#REF!-#REF!-#REF!+#REF!+#REF!-#REF!-#REF!+#REF!-#REF!+#REF!-#REF! -> #REF! | C96: 1234480.2
A97: Total | B97: =SUM(B93:B96) -> #REF! | C97: =SUM(C93:C96) -> 1.4416602e+08
A99: Note 9 Program expenses
A100: Asset Purchases From Restricted Funds | B100: =#REF!-#REF! -> #REF! | C100: 1032818
A101: Bank Charges | B101: =#REF!-#REF! -> #REF! | C101: 59422.18
A102: Catering & Pantry Expenses | B102: =#REF!-#REF! -> #REF! | C102: 2316140
A103: Centre Setup & Shifting Expenses | B103: =#REF!-#REF! -> #REF! | C103: 739533.2
A104: Computer Maintenance | B104: =#REF!-#REF! -> #REF! | C104: 305767.4
A105: Electricity & Water | B105: =#REF!-#REF!+#REF!-#REF! -> #REF! | C105: 520523.6
A106: Housekeeping, Repairs & Maintenance | B106: =#REF!-#REF!+#REF!+#REF!-#REF!-#REF!+#REF!-#REF!+#REF!-#REF!+#REF!-#REF! -> #REF! | C106: =884685.94+714822.05 -> 1599508
A107: Interest on Unutilised Grants | B107: =#REF!-#REF! -> #REF! | C107: 2461697
A108: Medical Expenses | B108: =#REF!-#REF! -> #REF! | C108: 36447.5
A109: Membership Fees | B109: =#REF! -> #REF! | C109: 309400
A110: Miscelleneous Expenses | B110: =#REF!-#REF! -> #REF! | C110: 3119
A111: Monitoring & Supervision Cost | B111: =#REF!-#REF!+#REF!-#REF! -> #REF! | C111: 0
A112: Outreach Expenses | B112: =SUM(#REF!)-SUM(#REF!) -> #REF! | C112: 4265352.5
A113: Postage, Telephone & Internet Expenses | B113: =#REF!-#REF!+#REF!-#REF! -> #REF! | C113: 408210.19
A114: Printing and stationery | B114: =#REF!-#REF! -> #REF! | C114: 32397.06
A115: Rent | B115: =#REF!-#REF!+#REF!-#REF! -> #REF! | C115: 12138805
A116: Software Subscription | B116: =#REF!-#REF! -> #REF! | C116: 1615636.1
A117: Staff Training, Recruitment & HR Expenses | B117: =SUM(#REF!)-SUM(#REF!)+#REF!-#REF!+#REF!-#REF! -> #REF! | C117: 22154452
A118: Training Materials & Other Expenses | B118: =#REF!-#REF! -> #REF! | C118: 271809.29
A119: Training Partner Expenses | B119: =#REF!-#REF! -> #REF! | C119: 13119286
A120: Training Software, Impact Tracking & Psychometric Expenses | B120: =#REF!-#REF!+#REF!-#REF!+#REF!-#REF! -> #REF! | C120: 6202338.8
A121: Travelling and conveyance | B121: =#REF!+#REF!+#REF!+SUM(#REF!)-SUM(#REF!)-#REF!-#REF!-#REF! -> #REF! | C121: 4266716.9
A122: Total Program Expenses | B122: =SUM(B100:B121) -> #REF! | C122: =SUM(C100:C121) -> 73859380
A125: Note 10 General Expenses
A126: Remuneration to Auditors - Audit Fees
A127: (i) Audit Fees | B127: =#REF! -> #REF! | C127: 173250
A128: (ii) Other Services | B128: =#REF! -> #REF! | C128: 8850
A129: Commission | B129: =#REF! -> #REF! | C129: 0
A130: Legal Charges | B130: =#REF! -> #REF! | C130: 0
A131: Loss on sale / discarding of asset | B131: =#REF! -> #REF! | C131: 51703
A132: Miscelleneous Expenses | B132: 0 | C132: 0
A133: Penalty on premature FD withdrawal | B133: =#REF! -> #REF! | C133: 0
A134: Professional Charges | B134: =#REF!+#REF!-#REF! -> #REF! | C134: 519910
A135: Rates & Taxes | B135: =#REF!+#REF!+#REF! -> #REF! | C135: 352564
...

Sheet Note 12 Restricted Fund Movmnt
A1: SGBS UNNATI FOUNDATION
A2: Notes forming part of the financial statements
A4: Note 12: Restricted Fund Movement for the year and balance as on 31st March 2025
A6: Particulars | B6: Balance as on 01.04.2024 | C6: Funds Recd during FY 2024 2025 | D6: Total Funds for FY 2024-2025 | E6: Utilised for Expenses | F6: Utilised for Asset Purchases | G6: Utilisation for Expenses/Purchase of assets for FY 2024 2025 | H6: Balance as on 31.03.2025
B7: INR | C7: INR | D7: INR | E7: INR | F7: INR | G7: INR | H7: INR
A8: ABC Company | I8: c/fd
A9: XYZ Trust | I9: c/fd
A10: PQR Ltd
A13: Total | B13: =SUM(B8:B12) -> 0 | C13: =SUM(C8:C12) -> 0 | D13: =SUM(D8:D12) -> 0 | E13: =SUM(E8:E12) -> 0 | F13: =SUM(F8:F12) -> 0 | G13: =SUM(G8:G12) -> 0 | H13: =SUM(H8:H12) -> 0
A14: Atlas balances | B14: ='Notes 2 to 11'!C28 -> 0 | G14: =#REF! -> #REF! | H14: =#REF! -> #REF!
A15: Differences | B15: =B13-B14 -> 0 | G15: =G13-G14 -> #REF! | H15: =H13-H14 -> #REF!

Sheet Note 13 & 13A Fixed Assets
A1: SOCIAL FOUNDATION
A2: Notes forming part of the financial statements
A5: Note 13 | B5: FIXED ASSETS: GRANT FUNDS 2024 2025
A6: SN | B6: Description | C6: Op. Bal | D6: Additions | E6: Deletions | F6: Cl. Bal | G6: Depreciation | L6: WDV | M6: WDV
C7: 01.04.2024 | F7: 31.03.2025 | G7: Op Bal 01.04.2024 | H7: FY 2024 2025 | I7: Depreciation on deletions reversed | J7: Total Depreciation for the year | K7: Cl. Bal 31.03.2025 | L7: 31.03.2025 | M7: 31.03.2024
C8: INR | D8: INR | E8: INR | F8: INR | G8: INR | H8: INR | I8: INR | J8: INR | K8: INR | L8: INR | M8: INR
A9: 1 | B9: Computers | L9: =F9-K9 -> 0 | M9: =C9-G9 -> 0
A10: 2 | B10: Furniture & Fixtures | L10: =F10-K10 -> 0 | M10: =C10-G10 -> 0
A11: 3 | B11: Office Equipment | L11: =F11-K11 -> 0 | M11: =C11-G11 -> 0
B13: Grand Total | C13: =SUM(C8:C12) -> 0 | D13: =SUM(D8:D12) -> 0 | E13: =SUM(E8:E12) -> 0 | F13: =SUM(F8:F12) -> 0 | G13: =SUM(G8:G12) -> 0 | H13: =SUM(H8:H12) -> 0 | I13: =SUM(I8:I12) -> 0 | J13: =SUM(J8:J12) -> 0 | ... M13: =SUM(M8:M12) -> 0 | O13: FY | P13: depn | Q13: depn revd | R13: def grant | S13: def grant revd | T13: gen fund revd | U13: def grnt diff | V13: depn diff
B14: Atlas bal | D14: ='Notes 2 to 11'!B100 -> #REF! | F14: =#REF!-#REF! -> #REF! | K14: =#REF!-#REF! -> #REF! | L14: =#REF!-#REF! -> #REF! | N14: grant | O14: 2014-15 | P14: =106446+19527+16551 -> 142524 | Q14: =817186 -> 817186 | R14: 142524 | T14: 817186 | U14: =R14-S14 -> 142524 | V14: =P14-Q14 -> -674662 | W14: =V14+V17 -> -1254086
B15: Difference from Atlas | D15: =D13-D14 -> #REF! | F15: =F13-F14 -> #REF! | K15: =K13-K14 -> #REF! | L15: =L13-L14 -> #REF!
B16: Deferred grant as per B/S | L16: ='Notes 2 to 11'!B19 -> 0
B17: Difference from B/S | L17: =L13-L16 -> 0 | N17: grant | O17: 2015-16 | P17: =1616294+1456030+203869+341705 -> 3617898 | Q17: =4104650+92672 -> 4197322 | R17: =2001604+1616294 -> 3617898 | S17: =4104650+92672 -> 4197322 | U17: =R17-S17 -> -579424 | V17: =P17-Q17 -> -579424
A20: Note 13A | B20: FIXED ASSETS: SELF FUNDED 2024 2025 | N20: grant | O20: 2016-17 | P20: =1126629+709094+189930+429013 -> 2454666 | R20: =1328037+1126629 -> 2454666 | U20: =R20-S20 -> 2454666 | V20: =P20-Q20 -> 2454666
A21: SN | B21: Description | C21: Op. Bal | D21: Additions | E21: Deletions | F21: Cl. Bal | G21: Depreciation | L21: WDV | M21: WDV | N21: suf | O21: 2014-15 | P21: =834171 -> 834171 | Q21: 1755842 | U21: =R21-S21 -> 0 | V21: =P21-Q21 -> -921671 | W21: =V21+V22 -> -716186
C22: 01.04.2024 | F22: 31.03.2025 | G22: Op Bal 01.04.2024 | H22: FY 2024 2025 | I22: Depreciation on deletions reversed | J22: Total Depreciation for the year | K22: Cl. Bal 31.03.2025 | L22: 31.03.2025 | M22: 31.03.2024 | N22: suf | O22: 2015-16 | P22: =1333321 -> 1333321 | Q22: 1127836 | U22: =R22-S22 -> 0 | V22: =P22-Q22 -> 205485
C23: INR | D23: INR | E23: INR | F23: INR | G23: INR | H23: INR | I23: INR | J23: INR | K23: INR | L23: INR | M23: INR | N23: suf | O23: 2016-17 | P23: =23655+1070819 -> 1094474 | U23: =R23-S23 -> 0 | V23: =P23-Q23 -> 1094474
A24: 1 | B24: Computers | L24: =F24-K24 -> 0 | M24: =C24-G24 -> 0 | O24: total | P24: =SUM(P14:P23) -> 9477054 | Q24: =SUM(Q14:Q23) -> 7898186 | R24: =SUM(R14:R23) -> 6215088 | S24: =SUM(S14:S23) -> 4197322 | T24: =SUM(T14:T23) -> 817186 | U24: =R24-S24 -> 2017766 | V24: =P24-Q24 -> 1578868
A25: 2 | B25: Furniture & Fixtures | L25: =F25-K25 -> 0 | M25: =C25-G25 -> 0 | O25: Depn a/c bal | P25: =P24+S24-Q24-R24 -> -438898 | V25: =U24-V24 -> 438898
A26: 3 | B26: Land | L26: =F26-K26 -> 0 | M26: =C26-G26 -> 0
A27: 4 | B27: Office Equipment | L27: =F27-K27 -> 0 | M27: =C27-G27 -> 0
L28: =F28-K28 -> 0 | M28: =C28-G28 -> 0
B29: Grand Total | C29: =SUM(C23:C28) -> 0 | D29: =SUM(D23:D28) -> 0 | E29: =SUM(E23:E28) -> 0 | F29: =SUM(F23:F28) -> 0 | G29: =SUM(G23:G28) -> 0 | H29: =SUM(H23:H28) -> 0 | I29: =SUM(I24:I28) -> 0 | J29: =SUM(J24:J28) -> 0 | K29: =SUM(K23:K28) -> 0 | L29: =SUM(L23:L28) -> 0 | M29: =SUM(M23:M28) -> 0
B30: Atlas bal | F30: =#REF! -> #REF! | K30: =#REF!-#REF! -> #REF! | L30: =#REF!-#REF! -> #REF!
B31: Difference from Atlas | F31: =F29-F30 -> #REF! | K31: =K29-K30 -> #REF! | L31: =L29-L30 -> #REF!
B32: Total WDV | L32: =L29+L13 -> 0
B33: Total as per Trial Balance | L33: =SUM(#REF!)-SUM(#REF!) -> #REF!
B34: Difference fom B/S | L34: =L32-L33 -> #REF!

Sheet Cash Flow
A1: SOCIAL FOUNDATION
A2: CIN:
A3: Address:
A4: Cash Flow Statement for the year ended 31st March, 2025
A7: Particulars | C7: For the year ended 31st March, 2025 | E7: For the year ended 31st March, 2024
C8: INR | D8: INR | E8: INR | F8: INR
A9: A. Cash flow from operating activities
A10: Excess of Income / (Expenditure) before extraordinary items and tax
B11: Adjustment for depreciation
A12: Excess of Income / (Expenditure) before working capital changes
A13: Changes in working capital:
A14: Adjustments for (increase) / decrease in operating assets:
A15: Short-term loans and advances, fixed deposits
A16: Receivables
A17: Non Current Assets
A18: Adjustments for increase / (decrease) in operating liabilities:
A19: Current liabilities
A22: Cash flow from extraordinary items / prior period adjustments
A23: Cash generated from operations
A24: Net income tax (paid) / refunds
A26: Net cash flow from / (used in) operating activities (A)
... A42: Cash and cash equivalents at the end of the year
D43: =D42-'Notes 2 to 11'!B57 -> #REF!
A44: See accompanying notes forming part of the financial statements
A45: As per our report of even date:
A46: For Auditor | C46: For and on behalf of the Board of Directors
A47: Chartered Accountants | C47: Social Foundation
A48: ICAI FR No:
A52: ='Balance Sheet'!A39 -> 0
A53: Partner | C53: Director | E53: Director
A54: ='Balance Sheet'!A41 -> ICAI MRN: | C54: DIN: | E54: DIN:
A55: ='Balance Sheet'!A42 -> UDIN:
A56: Place :
A57: ='Balance Sheet'!A44 -> Date :

Sheet Receipts & Payments
A1: SOCIAL FOUNDATION
A2: CIN:
A3: Address:
A5: RECEIPT AND PAYMENT ACCOUNT FOR THE YEAR ENDED 31.03.2025
G6: AMOUNT (Rs.)
A8: Opening Balances:
B9: Bank - 1 - Local
B10: Bank 2 - FCRA
A13: RECEIPTS:
A14: Donations & Grants
A15: Other Income
A16: Deposits Received
F17: Total | H17: =SUM(H11:H16) -> 0
A18: PAYMENTS:
A19: Program Expenses
A20: General & Admin Expenses
A21: Fixed Asset Purchases
A22: Advances & Deposits given
A25: Closing Balances:
B26: Bank - 1 - Local
B27: Bank 2 - FCRA
F28: Total | H28: 0 | I28: =H17-H28 -> 0
A30: As per our report of even date.
A31: for Auditor
A32: Chartered Accountants | F32: For and on behalf of the Board of Directors
A33: FRNo. | F33: Social Foundation
A36: ='Balance Sheet'!A39 -> 0
A37: Partner
A38: ='Balance Sheet'!A41 -> ICAI MRN: | F38: Director | G38: Director
A39: ='Balance Sheet'!A42 -> UDIN: | F39: DIN: | G39: DIN:
A40: Place:
A41: ='Balance Sheet'!A44 -> Date :

Sheet 26. Finance Costs
B2: Name of the Company
B3: Notes forming part of the financial statements
A5: GN 9.5.5 | B5: Note 26 Finance costs
A7: Ref. No. | B7: Particulars | C7: For the year ended 31 March, 20X2 | D7: For the year ended 31 March, 20X1
C8: ` | D8: `
A9: PL 3 (a) PL 5.i.(e) GN 9.5.5 A | B9: (a) Interest expense on:
B10: (i) Borrowings
B11: (ii) Trade payables
B12: (iii) Others
A13: GN 9.8.1.3 | B13: - Interest on delayed / deferred payment of income tax
B14: - Others (give details)
A16: PL 3 (b) GN 9.5.5 B | B16: (b) Other borrowing costs @
A18: PL 3 (c) GN 9.5.5 C AS 16.4.e | B18: (c) Net (gain) / loss on foreign currency transactions and translation (considered as finance cost)
B20: Total
A21: i | B21: @ Other borrowing costs would include commitment charges, loan processing charges, guarantee charges, loan facilitation charges, discounts / premiums on borrowings, other ancillary costs incurred in connection with borrowings or amortisation of such costs, etc.

Sheet 27. Other Expenses
B2: Name of the Company
B3: Notes forming part of the financial statements
A5: GN 9.5.7 | B5: Note 27 Other expenses
A7: Ref. No. | B7: Particulars | C7: For the year ended 31 March, 20X2 | D7: For the year ended 31 March, 20X1
C8: ` | D8: `
B9: Travelling and conveyance * | C9: =+#REF! -> #REF! | D9: 0
B10: Printing and stationery* | C10: =+#REF! -> #REF! | D10: 0
B11: Legal and professional * | C11: =+#REF! -> #REF! | D11: 0
B12: Charity ( Educational Assistance) | C12: =+#REF! -> #REF! | D12: 0
B13: Audit Fee | C13: 5000 | D13: 0
B14: Bank Charges | C14: =+#REF! -> #REF! | D14: 0
B15: Total | C15: =SUM(C9:C14) -> #REF! | D15: =SUM(D9:D14) -> 0
A16: GN 9.5.7 | B16: Note 27 Other expenses (contd.)
A18: Ref. No. | B18: Particulars
A19: i | B19: @ Consumption of packing materials which are not classified by the Company as part of raw materials should be disclosed separately under Other expenses.
A20: i | B20: # In case of net credit the amount should be included under Other operating revenue in Note 22 Revenue from operations or under Other income in Note 23, as applicable.
A21: i | B21: If an impairment loss is recognised or reversed by the Company, then additional disclosures as required under AS 28 Impairment of Assets needs to be given.
A22: i | B22: Wealth tax and penalties levied under Income Tax laws should not be classified as current tax and should be disclosed under Note 27 Other expenses as part of Rates and taxes.
A23: i | B23: Certain donations need to be disclosed as required under Section 293A / 293B of the Companies Act, 1956.
B24: Notes:
B25: Particulars | C25: For the year ended 31 March, 20X2 | D25: For the year ended 31 March, 20X1
C26: ` | D26: `
A27: PL 5(i)(j) GN 10.3 | B27: (i) Payments to the auditors comprises (net of service tax input credit, where applicable):
B28: As auditors - statutory audit
B29: For taxation matters
B30: For company law matters
B31: For management services
B32: For other services
B33: Reimbursement of expenses
B34: Total
A35: i | B35: Payments for - taxation matters would include tax audit fees, certifications under the Income Tax Act, tax advisory services, etc. - company law matters would include certifications (e.g. certificate for buy-back of shares, etc.), company law advisory services, etc. - other services would include limited reviews, group reporting, other attest services and certifications under other laws, etc.
A36: PL 5(i)(l) | B36: (ii) Details of Prior period items (net)
A37: GN 10.4 | B37: Prior period expenses (give details)
B38: Prior period income (give details)
B39: Total
A40: PL5(i)(c) | B40: ? * Any item of expenditure which exceeds 1% of the revenue from operations or ` 100,000/- whichever is higher should be disclosed. Items which do not meet the criteria may be included as part of Miscellaneous expenses.

Sheet 28. Exceptional & Extraordinary
B2: Name of the Company
B3: Notes forming part of the financial statements
A5: GN 9.6 | B5: Note 28.a Exceptional items @
A7: Ref. No. | B7: Particulars | C7: For the year ended 31 March, 20X2 | D7: For the year ended 31 March, 20X1
C8: ` | D8: `
A9: PL 5.i.k
A10: AS 5.12 AS 5.13 AS 5.14 | B10: (Give details)
B13: Total
A14: i | B14: @ Exceptional items are items of income and expenses which are of such size, nature or incidence that their disclosure (giving details) is relevant to explain the performance of the Company.
A16: GN 9.7 | B16: Note 28.b Extraordinary items #
A18: Ref. No. | B18: Particulars | C18: For the year ended 31 March, 20X2 | D18: For the year ended 31 March, 20X1
C19: ` | D19: `
A20: PL 5.i.k
A21: AS 5.4.2 AS 5.8 | B21: (Give details)
A22: AS 12.20 | B22: Government grants that have become refundable
B24: Total
A25: i | B25: # Extraordinary items are income and expenses that arise from events or transactions that are clearly distinct from ordinary activities of the Company and are not expected to recur frequently or regularly.

Sheet 29. Addl Info to the FS 
B2: Name of the Company
B3: Notes forming part of the financial statements
A5: GN 6.13 | B5: Note 29 Additional information to the financial statements
A7: Ref. No. | B7: Note | C7: Particulars
B9: 29.1 | C9: Monies received against share warrants
A10: BS 6.A.h GN 8.1.3 | C10: The Board of Directors of the Company at their meeting held on X July, 20XX and as approved at its Annual General Meeting held on XX July, 20XX have resolved to create, offer, issue and allot up to _____ warrants, convertible into _____ equity shares of ` __/- each on a preferential allotment basis, pursuant to Section 81(1A) of the Companies Act, 1956, at a conversion price of ` ___/- per equity share of the Company, arrived at in accordance with the SEBI Guidelines in this regard and subsequently these warrants were allotted on (date) to the promoters and the 10% application money amounting to ` ______ was received from them. The warrants may be converted into equivalent number of shares on payment of the balance amount at any time on or before 31 July, 20XX. In the event the warrants are not converted into shares within the said period, the Company is eligible to forfeit the amounts received towards the warrants.
B12: 29.2 | C12: Share application money pending allotment
A13: BS 6.A.h GN 8.2 | C13: As at 31 March 20X2, the Company has received an amount of `_____ towards share application money towards ____ equity / preference shares of the Company (As at 31 March, 20X1 ` ____ towards ____ equity/preference shares) at a premium of ` ____ (As at 31 March, 20X1 ` ____). The share application money was received pursuant to an invitation to offer shares and in terms of such invitation, the Company is required to complete the allotment formalities by _____ (As at 31 March, 20X1 ______). The Company has sufficient authorised capital to cover the allotment of these shares. Pending allotment of shares, the amounts are maintained in a designated bank account and is not available for use by the Company.
A14: GN 8.2.3 | C14: ? Give details of the terms and conditions, number of shares proposed to be issued, the amount of premium, if any, the period before which the shares are to be allotted, whether the Company has sufficient authorised capital to allot the shares and the period beyond which the share application money is pending allotment with the reasons therefor, where applicable.
E16: As at 31 March, 20X2 | F16: As at 31 March, 20X1
E17: ` | F17: `
B18: 29.3 | C18: Contingent liabilities and commitments (to the extent not provided for)
A19: BS 6.T.i | B19: (i) | C19: Contingent liabilities
A20: AS 29.68 GN 8.8.7.1 | C20: (a) Claims against the Company not acknowledged as debt (give details)
A21: GN 8.8.7.2 | C21: (b) Guarantees @ (give details)
C22: (c) Other money for which the Company is contingently liable (give details)
A23: AS 29.71 | C23: ? The Company should disclose for each class of contingent liability, the estimated financial effect, the uncertainties relating to any outflow, the possibility of any reimbursement and any asset recognised therefor. If the Company is unable to disclose this information because it is not practicable to do so, that fact should be disclosed.
A24: AS 29.72 | C24: ? In extremely rare cases, disclosures of some or all information relating to contingent liabilities that are required to be presented may prejudice seriously the position of the Company. In such cases, the Company need not disclose the information but should disclose the general nature of the dispute, together with the fact that, the information has not been disclosed and the reason therefor.
E25: As at 31 March, 20X2 | F25: As at 31 March, 20X1
A26: BS 6.T.ii GN 8.8.7.3 | B26: (ii) | C26: Commitments # | E26: ` | F26: `
C27: (a) Estimated amount of contracts remaining to be executed on capital account and not provided for
C28: Tangible assets
A29: AS 26.94.d | C29: Intangible assets
C30: (b) Uncalled liability on shares and other investments partly paid
A31: GN 8.8.7.4 GN 8.8.7.6 | C31: (c) Other commitments (specify nature)
A34: GN 6.13 | B34: Note 29 Additional information to the financial statements (contd.)
A36: Ref. No. | B36: Note | C36: Particulars
A38: i | C38: @ A contingent liability in respect of guarantees arises when the Company issues guarantees to another person on behalf of a third party. However, where the Company undertakes to perform its own obligations, and for this purpose issues, what is called a 'guarantee', it does not represent a contingent liability and it would be misleading to show such items as contingent liabilities in the Balance Sheet. It is also customary for guarantees to be issued by its bankers on behalf of the Company. For this purpose, the Company issues a 'counter-guarantee' to its bankers. Such 'counter-guarantee' is not really a guarantee at all, but is an undertaking to perform what is in any event the obligation of the Company. Hence, such performance guarantees and counter guarantees should not be disclosed as contingent liabilities.
A39: i | C39: # The word ‘commitment’ has not been defined in the Revised Schedule VI. 'Other commitments' would include all expenditure related contractual commitments such as commitments arising from long-term contracts for purchase of raw material, employee contracts, lease commitments, etc. The scope of such terminology is very wide and may include contractual commitments for purchase of inventory, services, investments, sales, employee contracts, etc. However, to give disclosure of all contractual commitments would be contrary to the overarching principle under General Instructions that “a balance shall be maintained between providing excessive detail that may not assist users of financial statements and not providing important information as a result of too much aggregation.” Accordingly, the disclosures required to be made for ‘other commitments’ should include only those non-cancellable contractual commitments (i.e. cancellation of which will result in a penalty disproportionate to the benefits involved) based on the professional judgment of the Management which are material and relevant in understanding the financial statements of the Company and impact the decision making of the users of financial statements. Examples may include commitments in the nature of buy-back arrangements, commitments to fund subsidiaries and associates, non-disposal of investments in subsidiaries and undertakings, derivative related commitments, etc.
A41: BS 6.V GN 8.8.7.8 | B41: 29.4 | C41: Details of unutilised amounts out of issue of securities made for specific purpose
C42: The Company had issued securities (specify type of security) amounting to ` ____ for purposes of _____. As at 31 March, 20X2, an amount of ` ____ (31 March, 20X1 ` ____) is pending utilisation in future periods / is no longer required for the said purpose consequent to completion of the specified activity. Accordingly, the unutilised amount has been invested in term deposits with banks (specify any other nature) / used in the operations of the Company for acquisition of other assets / investments / to meet its working capital requirements.
A44: GN 6.8 GN 8.4.2 GN 8.4.3 | B44: 29.5 | C44: Disclosures required under Section 22 of the Micro, Small and Medium Enterprises Development Act, 2006
C45: Particulars | E45: As at 31 March, 20X2 | F45: As at 31 March, 20X1
E46: ` | F46: `
C47: (i) Principal amount remaining unpaid to any supplier as at the end of the accounting year
C48: (ii) Interest due thereon remaining unpaid to any supplier as at the end of the accounting year
C49: (iii) The amount of interest paid along with the amounts of the payment made to the supplier beyond the appointed day
C50: (iv) The amount of interest due and payable for the year
C51: (v) The amount of interest accrued and remaining unpaid at the end of the accounting year
C52: (vi) The amount of further interest due and payable even in the succeeding year, until such date when the interest dues as above are actually paid
C53: Dues to Micro and Small Enterprises have been determined to the extent such parties have been identified on the basis of information collected by the Management. This has been relied upon by the auditors.
A55: Listing Clause | B55: 29.6 | C55: Disclosure as per Clause 32 of the Listing Agreements with the Stock Exchanges
A56: GN 6.9 | C56: Loans and advances in the nature of loans given to subsidiaries, associates and others and investment in shares of the Company by such parties:
C57: Name of the party | D57: Relationship | E57: Amount outstanding as at 31 March, 20X2 | F57: Maximum balance outstanding during the year
E58: AAA | F58: BBB
E59: (XXX) | F59: (YYY)
C61: Note: Figures in bracket relate to the previous year.
A63: GN 6.13 | B63: Note 29 Additional information to the financial statements (contd.)
A65: Ref. No. | B65: Note | C65: Particulars
A67: Other Ann / Gn | B67: 29.7 | C67: Details on derivatives instruments and unhedged foreign currency exposures
A68: GN 6.9 | C68: I. The following derivative positions are open as at 31 March, 20X2. These transactions have been undertaken to act as economic hedges for the Company’s exposures to various risks in foreign exchange markets and may / may not qualify or be designated as hedging instruments. The accounting for these transactions is stated in Notes 2.11, 2.26 and 2.27.
C69: (a) Forward exchange contracts and options [being derivative instruments], which are not intended for trading or speculative purposes but for hedge purposes to establish the amount of reporting currency required or available at the settlement date of certain payables and receivables.
C70: (i) Outstanding forward exchange contracts entered into by the Company as on 31 March, 20X2
C71: Currency | D71: Amount | E71: Buy / Sell | F71: Cross currency
C72: AUD | D72: XXX | E72: Buy | F72: Rupees
C73: AUD | D73: (AAA) | E73: Buy | F73: Rupees
C74: USD | D74: YYY | E74: Sell | F74: Rupees
C75: USD | D75: (ZZZ) | E75: Sell | F75: Rupees
C76: Note: Figures in brackets relate to the previous year
C78: (ii) Outstanding option contracts entered into by the Company as on 31 March, 20X2
C79: Currency | D79: Amount | E79: Buy / Sell | F79: Cross currency
C80: AUD | D80: XXX | E80: Buy | F80: Rupees
C81: AUD | D81: (AAA) | E81: Buy | F81: Rupees
C82: USD | D82: YYY | E82: Sell | F82: Rupees
C83: USD | D83: (ZZZ) | E83: Sell | F83: Rupees
C84: Note: Figures in brackets relate to the previous year
C86: (b) Interest rate swaps to hedge against fluctuations in interest rate changes: No. of contracts: Nil (As at 31 March, 20X1: Nil )
C87: (c) Currency swaps (other than forward exchange contracts stated above) to hedge against fluctuations in changes in exchange rate. No. of contracts: Nil (As at 31 March, 20X1: Nil)
C88: II. The year-end foreign currency exposures that have not been hedged by a derivative instrument or otherwise are given below:
C89: As at 31 March, 20X2 | E89: As at 31 March, 20X1
C90: Receivable/ | D90: Receivable/ (Payable) | E90: Receivable/ | F90: Receivable/ (Payable)
C91: (Payable) | D91: in Foreign currency | E91: (Payable) | F91: in Foreign currency
C92: ` | D92: (indicate amount with currency) | E92: ` | F92: (indicate amount with currency)
A96: GN 6.9 | B96: 29.8 | C96: Disclosure required in terms of Clause 13.5A of Chapter XIII on Guidelines for preferential issues, SEBI (Disclosure and Investor Protection) Guidelines, 2000
C97: Particulars | E97: During the year ended 31 March, 20X2
E98: ` | F98: `
C99: Total amount received from issue of fully convertible debentures | E99: aaa
C100: Total amount received from issue of warrants | E100: bbb | F100: xxx
C101: Purpose for which the money received has been utilized :
C102: a. Capital expenditure | E102: ppp
C103: b. Working capital | E103: qqq | F103: rrr
C106: Unutilised monies as at 31 March, 20X2 | F106: xyz
B108: 29.9 | C108: Details of fixed assets held for sale | E108: As at 31 March, 20X2 | F108: As at 31 March, 20X1
E109: ` | F109: `
C110: Building
C111: Plant and machinery
C112: Office equipment
C113: Vehicles
C114: Others (give details)
C115: Total
A117: GN 6.13 | B117: Note 29 Additional information to the financial statements (contd.)
A119: Ref. No. | B119: Note | C119: Particulars
A121: PL 5(viii)(a) GN 11.1 | B121: 29.10 | C121: Value of imports calculated on CIF basis @: | E121: For the year ended 31 March, 20X2 | F121: For the year ended 31 March, 20X1
E122: ` | F122: `
C124: Raw materials
C126: Components
C127: Spare parts
C128: Total Components and spare parts
C130: Capital goods
A131: i | C131: @ The following guidance, summarised based on the ICAI Guidance Note on Revised Schedule VI, may be considered in presenting the disclosures under this clause: (a) The total value of imported components and spare parts may be presented in the aggregate or sub-classified and presented. Where records of raw materials and components are maintained together, the information relating to components may be presented together with raw materials. (b) The clause requires only disclosure of imported spare parts and not stores. If it is not practical for the Company to segregate imported stores and spare parts, the total value of import of stores and spare parts may be shown clearly describing that the value disclosed relates to imported stores and spare parts. (c) The disclosure relates to imports of goods and not consumption. The disclosure should be made on accrual basis. Accordingly, the disclosure should include goods in transit. The disclosure should also be made irrespective of whether the imports have resulted in an expenditure in foreign currency. The disclosure should be made in Indian Rupees. (d) Disclosure is with regard to 'direct' imports by the Company.
...

Sheet 30.1 AS 7 Disclosures
B2: Name of the Company
B3: Notes forming part of the financial statements
A5: GN 6.13 | B5: Note 30 Disclosures under Accounting Standards
A7: Ref. No. | B7: Note | C7: Particulars | D7: For the year ended 31 March, 20X2 | E7: For the year ended 31 March, 20X1
D8: ` | E8: `
A9: AS 7 | B9: 30.1 | C9: Details of contract revenue and costs
A10: AS 7.38.a | C10: Contract revenue recognised during the year
A11: AS 7.39.a | C11: Aggregate of contract costs incurred and recognised profits (less recognised losses) upto the reporting date
A12: AS 7.39.b | C12: Advances received for contracts in progress
A13: AS 7.39.c | C13: Retention money for contracts in progress
A14: AS 7.41.a | C14: Gross amount due from customers for contract work (asset)
A15: AS 7.41.b | C15: Gross amount due to customers for contract work (liability)

Sheet 30.2 AS 12 Disclosures
B2: Name of the Company
B3: Notes forming part of the financial statements
A5: GN 6.13 | B5: Note 30 Disclosures under Accounting Standards (contd.)
A7: Ref. No. | B7: Note | C7: Particulars | D7: For the year ended 31 March, 20X2 | E7: For the year ended 31 March, 20X1
D8: ` | E8: `
A9: AS 12 | B9: 30.2 | C9: Details of government grants
A10: AS 12.23.ii | B10: 30.2.a | C10: Government grants received by the Company during the year towards
C11: - Subsidies (recognised under _____)
C12: - Duty drawback (recognised under Other operating revenues)
C13: - Other incentives (specify nature) (recognised under ____)
B15: 30.2.b | C15: The Company has received certain equipments and facilities free of cost from ____ towards carrying on research and development. These assets are required to be returned on completion of the specified activity.

Sheet 30.3 AS 14 Disclosures
B2: Name of the Company
B3: Notes forming part of the financial statements
A5: GN 6.13 | B5: Note 30 Disclosures under Accounting Standards (contd.)
A7: Ref. No. | B7: Note | C7: Particulars
A9: AS 14 | B9: 30.3 | C9: Details of amalgamations
A11: AS 14.43 | C11: In terms of the Scheme of Arrangement (the Scheme), __________ and __________________, both subsidiaries of the Company (referred to as ‘Transferor Companies’), have been merged with the Company (Transferee Company), upon which the undertaking and the entire business, including all assets and liabilities of the Transferor Companies stand transferred to and vested in the Transferee Company at their fair value as determined by the Board of Directors of the Transferee Company (or alternatively at their book values). ____ and ______ were engaged in the manufacture of _________________ and were predominantly acting as a captive manufacturer for the Company. The Scheme of Arrangement filed by the Company has been approved by the Honourable High Courts of Judicature at Mumbai, Chennai and Bangalore with an appointed date of 1 January, 200X and an effective date of 31 December, 200X (‘the Effective Date’), being the date on which all the requirements under the Companies Act, 1956 have been completed.
C12: Pursuant to the Scheme, the Company allotted ____ equity shares of ` __/- each (__% of shares in the Transferor Company and ___% of shares in the Transferee Company) to the minority shareholders in the Transferor Companies.
A13: AS 14.45 | C13: Details of assets and liabilities acquired on amalgamation and treatment of the difference between the net assets acquired and cost of investment by the Transferee Company in the Transferor Companies together with the shares issued to the minority shareholders:
D14: Year ended 31 March, 20X2
C15: Value of assets and liabilities acquired: | D15: ` | E15: `
C16: Fixed assets | D16: aaa
C17: Net current assets (give details) | D17: bbb
C18: Secured loans | D18: ccc
C19: Unsecured loans | D19: ddd | E19: XXX
C21: Less:
C22: Carrying value of investments in the Transferor Companies | D22: eee
C23: Value of shares of the Company issued to the minority shareholders | D23: hhh | E23: YYY
C25: Difference considered as goodwill / capital reserve | E25: QQQ

Sheet 30.4 AS 15 Disclosures
B2: Name of the Company
B3: Notes forming part of the financial statements
A5: GN 6.13 | B5: Note 30 Disclosures under Accounting Standards (contd.)
A7: Ref. No. | B7: Note | E7: Particulars
A9: AS 15 | B9: 30.4 | C9: Employee benefit plans
A10: AS 15.47 | B10: 30.4.a | C10: Defined contribution plans
C11: The Company makes Provident Fund and Superannuation Fund contributions to defined contribution plans for qualifying employees. Under the Schemes, the Company is required to contribute a specified percentage of the payroll costs to fund the benefits. The Company recognised ` ___________ (Year ended 31 March, 20X1 ` __________) for Provident Fund contributions and ` _____ (Year ended 31 March, 20X1 ` _______) for Superannuation Fund contributions in the Statement of Profit and Loss. The contributions payable to these plans by the Company are at rates specified in the rules of the schemes.
A12: i | C12: In case the company has contributions to foreign defined contribution plans and benefit plans, the details of the same should be disclosed.
A13: AS 15.120.b | B13: 30.4.b | C13: Defined benefit plans
C14: The Company offers the following employee benefit schemes to its employees:
C15: i. Gratuity
C16: ii. Post-employment medical benefits
C17: iii. Other defined benefit plans (specify nature)
C18: The following table sets out the funded status of the defined benefit schemes and the amount recognised in the financial statements:
I19: `
C20: Particulars | D20: Year ended 31 March, 20X2 | G20: Year ended 31 March, 20X1
D21: Gratuity | E21: Post-employment medical benefits | F21: Other defined benefit plans (specify nature) | G21: Gratuity | H21: Post-employment medical benefits | I21: Other defined benefit plans (specify nature)
A22: AS 15.120.g | C22: Components of employer expense
C23: Current service cost
C24: Interest cost
C25: Expected return on plan assets
C26: Curtailment cost / (credit)
C27: Settlement cost / (credit)
C28: Past service cost
C29: Actuarial losses/(gains)
C30: Total expense recognised in the Statement of Profit and Loss
C32: Actual contribution and benefit payments for year
C33: Actual benefit payments
C34: Actual contributions
A36: AS 15.120.f | C36: Net asset / (liability) recognised in the Balance Sheet
A37: AS 15.120.d | C37: Present value of defined benefit obligation
C38: Fair value of plan assets
C39: Funded status [Surplus / (Deficit)]
C40: Unrecognised past service costs
C41: Net asset / (liability) recognised in the Balance Sheet
A42: GN 6.13 | B42: Note 30 Disclosures under Accounting Standards (contd.)
I43: `
A44: Ref. No. | B44: Note | C44: Particulars | D44: Year ended 31 March, 20X2 | G44: Year ended 31 March, 20X1
D45: Gratuity | E45: Post-employment medical benefits | F45: Other defined benefit plans (specify nature) | G45: Gratuity | H45: Post-employment medical benefits | I45: Other defined benefit plans (specify nature)
A47: AS 15.120.c | C47: Change in defined benefit obligations (DBO) during the year
C48: Present value of DBO at beginning of the year
C49: Current service cost
C50: Interest cost
C51: Curtailment cost / (credit)
C52: Settlement cost / (credit)
C53: Plan amendments
C54: Acquisitions
C55: Actuarial (gains) / losses
C56: Past service cost
C57: Benefits paid
C58: Present value of DBO at the end of the year
A60: AS 15.120.e | C60: Change in fair value of assets during the year
C61: Plan assets at beginning of the year
C62: Acquisition adjustment
C63: Expected return on plan assets
C64: Actual company contributions
C65: Actuarial gain / (loss)
C66: Benefits paid
C67: Plan assets at the end of the year
A69: AS 15.120.k | C69: Actual return on plan assets
A71: AS 15.120.h | C71: Composition of the plan assets is as follows:
C73: Government bonds
C74: PSU bonds
C75: Equity mutual funds
C76: Others
A78: AS 15.120.l | C78: Actuarial assumptions
C79: Discount rate
A80: AS 15.120.j | C80: Expected return on plan assets
C81: Salary escalation
C82: Attrition
C83: Medical cost inflation
C84: Mortality tables
C85: Performance percentage considered
A86: AS 15.120.o | C86: Estimate of amount of contribution in the immediate next year
A87: GN 6.13 | B87: Note 30 Disclosures under Accounting Standards (contd.)
A89: Ref. No. | B89: Note | C89: Particulars
A90: AS 15.120.j | C90: The discount rate is based on the prevailing market yields of Government of India securities as at the Balance Sheet date for the estimated term of the obligations.
A91: AS 15.120.l | C91: The estimate of future salary increases considered, takes into account the inflation, seniority, promotion, increments and other relevant factors.
C93: Effect of a 1% change in health care cost | D93: 31 March, 20X2 | F93: 31 March, 20X1
A94: AS 15.120.m | D94: Increase by 1% | E94: Decrease by 1% | F94: Increase by 1% | G94: Decrease by 1%
C96: Aggregate current service and interest cost
C97: Closing balance of obligation
A99: AS 15.120.n | C99: Experience adjustments | H99: `
D100: 20X2-20X1 | E100: 20X1- 20X0 | F100: 2nd prior year | G100: 3rd prior year | H100: 4th prior year
C101: Gratuity
C102: Present value of DBO
C103: Fair value of plan assets
C104: Funded status [Surplus / (Deficit)]
C105: Experience gain / (loss) adjustments on plan liabilities
C106: Experience gain / (loss) adjustments on plan assets
C107: Post Employment medical Benefits
C108: Present value of DBO
C109: Fair value of plan assets
C110: Funded status [Surplus / (Deficit)]
C111: Experience gain / (loss) adjustments on plan liabilities
C112: Experience gain / (loss) adjustments on plan assets
... C118: Experience gain / (loss) adjustments on plan assets
D120: For the year ended 31 March, 20X2 | E120: For the year ended 31 March, 20X1
C121: Actuarial assumptions for long-term compensated absences
C122: Discount rate
...

Sheet 30.5 AS 16 Disclosures
B2: Name of the Company
B3: Notes forming part of the financial statements
A5: GN 6.13 | B5: Note 30 Disclosures under Accounting Standards (contd.)
A7: Ref. No. | B7: Note | C7: Particulars | D7: For the year ended 31 March, 20X2 | E7: For the year ended 31 March, 20X1
D8: ` | E8: `
A9: AS 16 | B9: 30.5 | C9: Details of borrowing costs capitalised
A10: AS 16.23.b | C10: Borrowing costs capitalised during the year
C11: - as fixed assets / intangible assets / capital work-in-progress
C12: - as inventory

Sheet 30.6 AS 17 Disclosures
B2: Name of the Company
B3: Notes forming part of the financial statements
A5: GN 6.13 | B5: Note 30 Disclosures under Accounting Standards (contd.)
A7: Ref. No. | B7: Note | C7: Particulars
A9: AS 17 | B9: 30.6 | C9: Segment information
A10: AS 17.58 | C10: The Company has identified business segments as its primary segment and geographic segments as its secondary segment. Business segments are primarily ______________ and ___________. Revenues and expenses directly attributable to segments are reported under each reportable segment. Expenses which are not directly identifiable to each reportable segment have been allocated on the basis of associated revenues of the segment and manpower efforts. All other expenses which are not attributable or allocable to segments have been disclosed as unallocable expenses. Assets and liabilities that are directly attributable or allocable to segments are disclosed under each reportable segment. All other assets and liabilities are disclosed as unallocable. Fixed assets that are used interchangeably amongst segments are not allocated to primary and secondary segments. Geographical revenues are allocated based on the location of the customer. Geographic segments of the Company are Americas (including Canada and South American countries), Europe, India and Others.
C11: Particulars | D11: For the year ended 31 March, 20X2
D12: Business segments | G12: Total
D13: A | E13: B | F13: Eliminations
D14: ` | E14: ` | F14: ` | G14: `
A15: AS 17.40.a | C15: Revenue | D15: YYY | E15: YYY | F15: YYY | G15: YYY
D16: (XXX) | E16: (XXX) | F16: (XXX) | G16: (XXX)
A17: AS 17.40.a | C17: Inter-segment revenue | D17: YYY | E17: YYY | F17: YYY | G17: YYY
D18: (XXX) | E18: (XXX) | F18: (XXX) | G18: (XXX)
C19: Total | D19: YYY | E19: YYY | F19: YYY | G19: YYY
D20: (XXX) | E20: (XXX) | F20: (XXX) | G20: (XXX)
A21: AS 17.40.b | C21: Segment result | D21: YYY | E21: YYY | F21: YYY | G21: YYY
D22: (XXX) | E22: (XXX) | F22: (XXX) | G22: (XXX)
A23: AS 17.46 | C23: Unallocable expenses (net) | G23: YYY
G24: (XXX)
C25: Operating income | G25: YYY
G26: (XXX)
C27: Other income (net) | G27: YYY
G28: (XXX)
C29: Profit before taxes | G29: YYY
G30: (XXX)
C31: Tax expense | G31: YYY
G32: (XXX)
C33: Net profit for the year | G33: YYY
G34: (XXX)
A36: GN 6.13 | B36: Note 30 Disclosures under Accounting Standards (contd.)
A38: Ref. No. | B38: Note | C38: Particulars | D38: For the year ended 31 March, 20X2
D39: Business segments | F39: Total
D40: A | E40: B
D41: ` | E41: ` | F41: `
A42: AS 17.40.c | C42: Segment assets | D42: YYY | E42: YYY | F42: YYY
D43: (XXX) | E43: (XXX) | F43: (XXX)
A44: AS 17.46 | C44: Unallocable assets | F44: YYY
F45: (XXX)
C46: Total assets | F46: YYY
F47: (XXX)
A49: AS 17.40.d | C49: Segment liabilities | D49: YYY | E49: YYY | F49: YYY
D50: (XXX) | E50: (XXX) | F50: (XXX)
A51: AS 17.46 | C51: Unallocable liabilities | F51: YYY
F52: (XXX)
C53: Total liabilities | F53: YYY
F54: (XXX)
C56: Other information
A57: AS 17.40.e | C57: Capital expenditure (allocable) | D57: YYY | E57: YYY | F57: YYY
D58: (XXX) | E58: (XXX) | F58: (XXX)
A59: AS 17.46 | C59: Capital expenditure (unallocable) | F59: YYY
F60: (XXX)
A61: AS 17.40.f | C61: Depreciation and amortisation (allocable) | D61: YYY | E61: YYY | F61: YYY
D62: (XXX) | E62: (XXX) | F62: (XXX)
A63: AS 17.46 | C63: Depreciation and amortisation (unallocable) | F63: YYY
F64: (XXX)
A65: AS 17.40.g | C65: Other significant non-cash expenses (allocable) (give details) | D65: YYY | E65: YYY | F65: YYY
D66: (XXX) | E66: (XXX) | F66: (XXX)
A67: AS 17.46 | C67: Other significant non-cash expenses (unallocable) | F67: YYY
F68: (XXX)
A71: GN 6.13 | B71: Note 30 Disclosures under Accounting Standards (contd.)
A73: Ref. No. | B73: Note | C73: Particulars
A75: AS 17.48 | C75: The geographic segments individually contributing 10 percent or more of the Company’s revenues and segment assets are shown separately:
C77: Geographic Segment | D77: Revenues For the year ended 31 March, 20X2 | E77: Segment assets As at 31 March, 20X2 | F77: Capital expenditure incurred during the year ended 31 March, 20X2
D78: ` | E78: ` | F78: `
C80: Americas | D80: YYY | E80: YYY | F80: YYY
D81: (XXX) | E81: (XXX) | F81: (XXX)
C82: Europe | D82: YYY | E82: YYY | F82: YYY
D83: (XXX) | E83: (XXX) | F83: (XXX)
C84: India | D84: YYY | E84: YYY | F84: YYY
D85: (XXX) | E85: (XXX) | F85: (XXX)
C86: Others | D86: YYY | E86: YYY | F86: YYY
D87: (XXX) | E87: (XXX) | F87: (XXX)
C89: Note: Figures in bracket relates to the previous year
A90: AS 17.58 | C90: ? Give composition of each geographical segment separately as a descriptive Note.

Sheet 30.7 AS 18 Disclosures
B2: Name of the Company
B3: Notes forming part of the financial statements
A5: GN 6.13 | B5: Note 30 Disclosures under Accounting Standards (contd.)
A7: Ref. No. | B7: Note | C7: Particulars
A9: AS 18 GN 6.15 | B9: 30.7 | C9: Related party transactions
B10: 30.7.a | C10: Details of related parties:
A11: AS 18.21 | C11: Description of relationship | D11: Names of related parties
A12: AS 18.23 | C12: Ultimate Holding Company | D12: AA Ltd.
C13: Holding Company | D13: A Ltd.
C14: Ultimate Holding Company | D14: AA Ltd.
C15: Subsidiaries | D15: B Ltd. and C (P) Ltd.
C16: Fellow Subsidiaries (to be given only if there are transactions) | D16: D Ltd. and Q Ltd.
C17: Associates | D17: X Ltd. and Y Ltd.
C18: Key Management Personnel (KMP) | D18: Mr. Y and Mr. Z
C19: Relatives of KMP | D19: Mrs. Y (wife of Mr. Y), Mr. F (father of Mr. Z)
C20: Company in which KMP / Relatives of KMP can exercise significant influence | D20: D Ltd in which MD(KMP) and his wife hold 50%
C21: Note: Related parties have been identified by the Management.
C22: Details of related party transactions during the year ended 31 March, 20X2 and balances outstanding as at 31 March, 20X2: | L22: `
A23: AS 18.23 | B23: 30.7.b | D23: Ultimate Holding Company | E23: Holding Company | F23: Subsidiaries | G23: Fellow Subsidiaries | H23: Associates | I23: KMP | J23: Relatives of KMP | K23: Entities in which KMP / relatives of KMP have significant influence | L23: Total
A24: AS 18.24 AS 18.26 | C24: ? Party-wise details - aggregation to be done only if the related party is < 10 % of the total amount of that particular type of transaction - e.g. purchases. Also note that in some cases even less than 10% will be required to be disclosed and such importance depends on circumstances of the respective companies.
C25: Purchase of goods | D25: YYY | E25: YYY | F25: YYY | G25: YYY | H25: YYY | I25: YYY | J25: YYY | K25: YYY | L25: YYY
D26: (XXX) | E26: (XXX) | F26: (XXX) | G26: (XXX) | H26: (XXX) | I26: (XXX) | J26: (XXX) | K26: (XXX) | L26: (XXX)
C27: Sale of goods | D27: YYY | E27: YYY | F27: YYY | G27: YYY | H27: YYY | I27: YYY | J27: YYY | K27: YYY | L27: YYY
D28: (XXX) | E28: (XXX) | F28: (XXX) | G28: (XXX) | H28: (XXX) | I28: (XXX) | J28: (XXX) | K28: (XXX) | L28: (XXX)
C29: Purchase of fixed assets | D29: YYY | E29: YYY | F29: YYY | G29: YYY | H29: YYY | I29: YYY | J29: YYY | K29: YYY | L29: YYY
D30: (XXX) | E30: (XXX) | F30: (XXX) | G30: (XXX) | H30: (XXX) | I30: (XXX) | J30: (XXX) | K30: (XXX) | L30: (XXX)
C31: Sale of fixed assets | D31: YYY | E31: YYY | F31: YYY | G31: YYY | H31: YYY | I31: YYY | J31: YYY | K31: YYY | L31: YYY
D32: (XXX) | E32: (XXX) | F32: (XXX) | G32: (XXX) | H32: (XXX) | I32: (XXX) | J32: (XXX) | K32: (XXX) | L32: (XXX)
C33: Rendering of services | D33: YYY | E33: YYY | F33: YYY | G33: YYY | H33: YYY | I33: YYY | J33: YYY | K33: YYY | L33: YYY
D34: (XXX) | E34: (XXX) | F34: (XXX) | G34: (XXX) | H34: (XXX) | I34: (XXX) | J34: (XXX) | K34: (XXX) | L34: (XXX)
C35: Receiving of services | D35: YYY | E35: YYY | F35: YYY | G35: YYY | H35: YYY | I35: YYY | J35: YYY | K35: YYY | L35: YYY
D36: (XXX) | E36: (XXX) | F36: (XXX) | G36: (XXX) | H36: (XXX) | I36: (XXX) | J36: (XXX) | K36: (XXX) | L36: (XXX)
C37: Agency arrangements | D37: YYY | E37: YYY | F37: YYY | G37: YYY | H37: YYY | I37: YYY | J37: YYY | K37: YYY | L37: YYY
D38: (XXX) | E38: (XXX) | F38: (XXX) | G38: (XXX) | H38: (XXX) | I38: (XXX) | J38: (XXX) | K38: (XXX) | L38: (XXX)
C39: Leasing or hire purchase arrangements | D39: YYY | E39: YYY | F39: YYY | G39: YYY | H39: YYY | I39: YYY | J39: YYY | K39: YYY | L39: YYY
D40: (XXX) | E40: (XXX) | F40: (XXX) | G40: (XXX) | H40: (XXX) | I40: (XXX) | J40: (XXX) | K40: (XXX) | L40: (XXX)
C41: Transfer of research and development | D41: YYY | E41: YYY | F41: YYY | G41: YYY | H41: YYY | I41: YYY | J41: YYY | K41: YYY | L41: YYY
D42: (XXX) | E42: (XXX) | F42: (XXX) | G42: (XXX) | H42: (XXX) | I42: (XXX) | J42: (XXX) | K42: (XXX) | L42: (XXX)
C43: License agreements | D43: YYY | E43: YYY | F43: YYY | G43: YYY | H43: YYY | I43: YYY | J43: YYY | K43: YYY | L43: YYY
D44: (XXX) | E44: (XXX) | F44: (XXX) | G44: (XXX) | H44: (XXX) | I44: (XXX) | J44: (XXX) | K44: (XXX) | L44: (XXX)
C45: Finance (including loans and equity contributions in cash or in kind) | D45: YYY | E45: YYY | F45: YYY | G45: YYY | H45: YYY | I45: YYY | J45: YYY | K45: YYY | L45: YYY
D46: (XXX) | E46: (XXX) | F46: (XXX) | G46: (XXX) | H46: (XXX) | I46: (XXX) | J46: (XXX) | K46: (XXX) | L46: (XXX)
C47: Guarantees and collaterals | D47: YYY | E47: YYY | F47: YYY | G47: YYY | H47: YYY | I47: YYY | J47: YYY | K47: YYY | L47: YYY
D48: (XXX) | E48: (XXX) | F48: (XXX) | G48: (XXX) | H48: (XXX) | I48: (XXX) | J48: (XXX) | K48: (XXX) | L48: (XXX)
C49: Management contracts including for deputation of employees | D49: YYY | E49: YYY | F49: YYY | G49: YYY | H49: YYY | I49: YYY | J49: YYY | K49: YYY | L49: YYY
D50: (XXX) | E50: (XXX) | F50: (XXX) | G50: (XXX) | H50: (XXX) | I50: (XXX) | J50: (XXX) | K50: (XXX) | L50: (XXX)
C51: Provision for doubtful receivables, loans and advances | D51: YYY | E51: YYY | F51: YYY | G51: YYY | H51: YYY | I51: YYY | J51: YYY | K51: YYY | L51: YYY
D52: (XXX) | E52: (XXX) | F52: (XXX) | G52: (XXX) | H52: (XXX) | I52: (XXX) | J52: (XXX) | K52: (XXX) | L52: (XXX)
C53: Write off / write back made during the year | D53: YYY | E53: YYY | F53: YYY | G53: YYY | H53: YYY | I53: YYY | J53: YYY | K53: YYY | L53: YYY
D54: (XXX) | E54: (XXX) | F54: (XXX) | G54: (XXX) | H54: (XXX) | I54: (XXX) | J54: (XXX) | K54: (XXX) | L54: (XXX)
C55: Balances outstanding at the end of the year
C57: Trade receivables | D57: YYY | E57: YYY | F57: YYY | G57: YYY | H57: YYY | I57: YYY | J57: YYY | K57: YYY | L57: YYY
D58: (XXX) | E58: (XXX) | F58: (XXX) | G58: (XXX) | H58: (XXX) | I58: (XXX) | J58: (XXX) | K58: (XXX) | L58: (XXX)
C59: Loans and advances | D59: YYY | E59: YYY | F59: YYY | G59: YYY | H59: YYY | I59: YYY | J59: YYY | K59: YYY | L59: YYY
D60: (XXX) | E60: (XXX) | F60: (XXX) | G60: (XXX) | H60: (XXX) | I60: (XXX) | J60: (XXX) | K60: (XXX) | L60: (XXX)
C61: Trade payables | D61: YYY | E61: YYY | F61: YYY | G61: YYY | H61: YYY | I61: YYY | J61: YYY | K61: YYY | L61: YYY
D62: (XXX) | E62: (XXX) | F62: (XXX) | G62: (XXX) | H62: (XXX) | I62: (XXX) | J62: (XXX) | K62: (XXX) | L62: (XXX)
C63: Borrowings | D63: YYY | E63: YYY | F63: YYY | G63: YYY | H63: YYY | I63: YYY | J63: YYY | K63: YYY | L63: YYY
D64: (XXX) | E64: (XXX) | F64: (XXX) | G64: (XXX) | H64: (XXX) | I64: (XXX) | J64: (XXX) | K64: (XXX) | L64: (XXX)
C65: Provision for doubtful receivables, loans and advances | D65: YYY | E65: YYY | F65: YYY | G65: YYY | H65: YYY | I65: YYY | J65: YYY | K65: YYY | L65: YYY
D66: (XXX) | E66: (XXX) | F66: (XXX) | G66: (XXX) | H66: (XXX) | I66: (XXX) | J66: (XXX) | K66: (XXX) | L66: (XXX)
C67: Note: Figures in bracket relates to the previous year

Sheet 30.8 AS 19 Disclosures
B2: Name of the Company
B3: Notes forming part of the financial statements
A5: GN 6.13 | B5: Note 30 Disclosures under Accounting Standards (contd.)
A7: Ref. No. | B7: Note | C7: Particulars | D7: For the year ended 31 March, 20X2 | E7: For the year ended 31 March, 20X1
D8: ` | E8: `
A9: AS 19 GN 8.8.7.5 | B9: 30.8 | C9: Details of leasing arrangements
A10: AS 19.46 | C10: As Lessor
A11: AS 19.46.d | B11: 30.8.a | C11: The Company has entered into operating lease arrangements for certain surplus facilities. The lease is non-cancellable for a period of ____ years from ____ and may be renewed for a further period of ___ years based on mutual agreement of the parties.
A12: AS 19.46.b | C12: Future minimum lease payments
C13: not later than one year
C14: later than one year and not later than five years
C15: later than five years
A17: AS 19.46.c | C17: Contingent rents recognised as income during the year (state basis)
A19: AS 19.46.a | C19: Depreciation recognised on the leased assets
C20: Impairment losses recognised on the leased assets
C21: Impairment losses reversed on the leased assets
A23: AS 19.37.f | B23: 30.8.b | C23: The Company has entered into finance lease arrangements for certain equipments and vehicles.
A24: AS 19.37.a | C24: Future minimum lease payments and reconciliation of gross investment in the lease and present value of minimum lease payments
C25: Future minimum lease payments
C26: not later than one year
C27: later than one year and not later than five years
C28: later than five years
A30: AS 19.37.b | C30: Less: Unearned finance income
A31: AS 19.37.a | C31: Present value of minimum lease payments receivable
C32: not later than one year
C33: later than one year and not later than five years
C34: later than five years
A36: AS 19.37.c | C36: Unguaranteed residual values accruing to the Company as the lessor
A37: AS 19.37.d | C37: Accumulated provision for doubtful minimum lease payments
A38: AS 19.37.e | C38: Contingent rents recognised as income during the year (state basis)
C40: As Lessee
A41: AS 19.22.f | B41: 30.8.c | C41: The Company has entered into finance lease arrangements for certain equipments and vehicles, which provide the Company an option to purchase the assets at the end of the lease period.
A42: AS 19.22.c | C42: Reconciliation of minimum lease payments
C43: Future minimum lease payments
C44: not later than one year
C45: later than one year and not later than five years
C46: later than five years
C48: Less: Unmatured finance charges
C49: Present value of minimum lease payments payable
C50: not later than one year
C51: later than one year and not later than five years
C52: later than five years
A54: AS 19.22.d | C54: Contingent rents recognised as expense during the year (state basis)
A56: As 19.22.e | C56: Future minimum sublease payments expected to be received under non-cancellable subleases
A58: AS 19.25.e | B58: 30.8.d | C58: The Company has entered into operating lease arrangements for certain facilities and office premises. The leases are non-cancellable and are for a period of ___ to ____ years and may be renewed for a further period of ___ years based on mutual agreement of the parties. The lease agreements provide for an increase in the lease payments by __ to ___% every ____ years.
A59: AS 19.25.a | C59: Future minimum lease payments
C60: not later than one year
C61: later than one year and not later than five years
C62: later than five years
A64: AS 19.25.c | C64: Lease payments recognised in the Statement of Profit and Loss
A65: AS 19.25.c | C65: Contingent rents recognised as expense during the year (state basis)
A67: AS 19.25.b | C67: Future minimum sublease payments expected to be received under non-cancellable subleases
A69: AS 19.25.d | C69: Sublease payments received / receivable recognised in the Statement of Profit and Loss
A71: AS 19.22.f.iii | C71: ? Restrictions imposed by lease arrangements, such as those concerning dividends, additional debt and further leasing should be disclosed.

Sheet 30.9 AS 20 Disclosures
B2: Name of the Company
B3: Notes forming part of the financial statements
A5: GN 6.13 | B5: Note 30 Disclosures under Accounting Standards (contd.)
A7: Ref. No. | B7: Note | C7: Particulars | D7: For the year ended 31 March, 20X2 | E7: For the year ended 31 March, 20X1
D8: ` | E8: `
A9: AS 20 | B9: 30.9 | C9: Earnings per share
C10: Basic
B11: 30.9.a | C11: Continuing operations
A12: AS 20.11 | C12: Net profit / (loss) for the year from continuing operations
A13: AS 20.11 | C13: Less: Preference dividend and tax thereon
A14: AS 20.48.ii | C14: Net profit / (loss) for the year from continuing operations attributable to the equity shareholders
A15: AS 20.48.ii | C15: Weighted average number of equity shares
A16: AS 20.48.ii | C16: Par value per share
A17: AS.20.50 | C17: Earnings per share from continuing operations - Basic
B19: 30.9.b | C19: Total operations
A20: AS 20.11 | C20: Net profit / (loss) for the year
A21: AS 20.11 | C21: Less: Preference dividend and tax thereon
A22: AS 20.48.ii | C22: Net profit / (loss) for the year attributable to the equity shareholders
A23: AS 20.48.ii | C23: Weighted average number of equity shares
A24: AS 20.48.ii | C24: Par value per share
C25: Earnings per share - Basic
C27: Basic (excluding extraordinary items)
B28: 30.9.c | C28: Continuing operations
A29: AS 20.11 | C29: Net profit / (loss) for the year from continuing operations
A30: AS 20.48.i | C30: (Add) / Less: Extraordinary items (net of tax) relating to continuing operations
A31: AS 20.11 | C31: Less: Preference dividend and tax thereon
A32: AS 20.48.ii | C32: Net profit / (loss) for the year from continuing operations attributable to the equity shareholders, excluding extraordinary items
A33: AS 20.48.ii | C33: Weighted average number of equity shares
A34: AS 20.48.ii | C34: Par value per share
A35: AS.20.48.i | C35: Earnings per share from continuing operations, excluding extraordinary items - Basic
B37: 30.9.d | C37: Total operations
A38: AS 20.11 | C38: Net profit / (loss) for the year
A39: AS 20.48.i | C39: (Add) / Less: Extraordinary items (net of tax)
A40: AS 20.11 | C40: Less: Preference dividend and tax thereon
A41: AS 20.48.ii | C41: Net profit / (loss) for the year attributable to the equity shareholders, excluding extraordinary items
A42: AS 20.48.ii | C42: Weighted average number of equity shares
A43: AS 20.48.ii | C43: Par value per share
A44: AS.20.48.i | C44: Earnings per share, excluding extraordinary items - Basic
C46: Diluted
C47: The diluted earnings per share has been computed by dividing the Net Profit After Tax available for Equity Shareholders by the weighted average number of equity shares, after giving dilutive effect of the outstanding Warrants, Stock Options and Convertible bonds for the respective periods. Since, the effect of the conversion of Preference shares was anti-dilutive, it has been ignored.
B49: 30.9.e | C49: Continuing operations
A50: AS 20.11 | C50: Net profit / (loss) for the year from continuing operations
A51: AS 20.11 | C51: Less: Preference dividend and tax thereon
A52: AS 20.48.ii | C52: Net profit / (loss) for the year attributable to the equity shareholders from continuing operations
A53: AS 20.29 | C53: Add: Interest expense and exchange fluctuation on convertible bonds (net)
A54: AS 20.48.ii | C54: Profit / (loss) attributable to equity shareholders from continuing operations (on dilution)
A55: AS 20.48.ii | C55: Weighted average number of equity shares for Basic EPS
A56: AS 20.48.ii | C56: Add: Effect of warrants, ESOPs and Convertible bonds which are dilutive
A57: AS 20.48.ii | C57: Weighted average number of equity shares - for diluted EPS
A58: AS 20.48.ii | C58: Par value per share
A59: AS.20.50 | C59: Earnings per share, from continuing operations - Diluted
A61: GN 6.13 | B61: Note 30 Disclosures under Accounting Standards (contd.)
A63: Ref. number | B63: Note | C63: Particulars | D63: For the year ended 31 March, 20X2 | E63: For the year ended 31 March, 20X1
D64: ` | E64: `
B65: 30.9.f | C65: Total operations
A66: AS 20.11 | C66: Net profit / (loss) for the year
A67: AS 20.11 | C67: Less: Preference dividend and tax thereon
A68: AS 20.48.ii | C68: Net profit / (loss) for the year attributable to the equity shareholders
A69: AS 20.29 | C69: Add: Interest expense and exchange fluctuation on convertible bonds (net)
A70: AS 20.48.ii | C70: Profit / (loss) attributable to equity shareholders (on dilution)
A71: AS 20.48.ii | C71: Weighted average number of equity shares for Basic EPS
A72: AS 20.48.ii | C72: Add: Effect of Warrants, ESOPs and Convertible bonds which are dilutive
A73: AS 20.48.ii | C73: Weighted average number of equity shares - for diluted EPS
A74: AS 20.48.ii | C74: Par value per share
C75: Earnings per share - Diluted
C77: Diluted (excluding extraordinary items)
B78: 30.9.g | C78: Continuing operations
A79: AS 20.11 | C79: Net profit / (loss) for the year from continuing operations
A80: AS 20.48.i | C80: (Add) / Less: Extraordinary items (net of tax)
A81: AS 20.11 | C81: Less: Preference dividend and tax thereon
A82: AS 20.48.ii | C82: Net profit / (loss) for the year from continuing operations attributable to the equity shareholders, excluding extraordinary items
A83: AS 20.29 | C83: Add: Interest expense and exchange fluctuation on convertible bonds (net)
A84: AS 20.48.ii | C84: Profit / (loss) from continuing operations attributable to equity shareholders (on dilution)
A85: AS 20.48.ii | C85: Weighted average number of equity shares for Basic EPS
A86: AS 20.48.ii | C86: Add: Effect of Warrants, ESOPs and Convertible bonds which are dilutive
A87: AS 20.48.ii | C87: Weighted average number of equity shares - for diluted EPS
A88: AS 20.48.ii | C88: Par value per share
A89: AS.20.50 | C89: Earnings per share, from continuing operations, excluding extraordinary items - Diluted
B91: 30.9.h | C91: Total operations
A92: AS 20.11 | C92: Net profit / (loss) for the year
A93: AS 20.48.i | C93: (Add) / Less: Extraordinary items (net of tax)
A94: AS 20.11 | C94: Less: Preference dividend and tax thereon
A95: AS 20.48.ii | C95: Net profit / (loss) for the year attributable to the equity shareholders, excluding extraordinary items
A96: AS 20.29 | C96: Add: Interest expense and exchange fluctuation on convertible bonds (net)
A97: AS 20.48.ii | C97: Profit / (loss) attributable to equity shareholders (on dilution)
A98: AS 20.48.ii | C98: Weighted average number of equity shares for Basic EPS
A99: AS 20.48.ii | C99: Add: Effect of Warrants, ESOPs and Convertible bonds which are dilutive
A100: AS 20.48.ii | C100: Weighted average number of equity shares - for diluted EPS
A101: AS 20.48.ii | C101: Par value per share
C102: Earnings per share, excluding extraordinary items - Diluted
A103: AS 20.8 | C103: ? Basic and diluted earnings per share should be presented on the face of the Statement of Profit and Loss for each class of equity shares that has a different right to share in the net profit for the period.
A104: AS 20.44 | C104: ? If the number of equity or potential equity shares outstanding increases as a result of bonus issue or share split or decreases as a result of reverse share split, the calculation of basic and diluted earnings per share should be adjusted for all the periods presented.

Sheet 30.10 AS 22 Disclosures 
B2: Name of the Company
B3: Notes forming part of the financial statements
A5: GN 6.13 | B5: Note 30 Disclosures under Accounting Standards (contd.)
A7: Ref. No. | B7: Note | C7: Particulars | D7: As at 31 March, 20X2 | E7: As at 31 March, 20X1
D8: ` | E8: `
A9: AS 22 GN 7.6 | B9: 30.10 | C9: Deferred tax (liability) / asset
A10: AS 22.31 | C10: Tax effect of items constituting deferred tax liability
C11: On difference between book balance and tax balance of fixed assets
C12: On expenditure deferred in the books but allowable for tax purposes
C13: On items included in Reserves and surplus pending amortisation into the Statement of Profit and Loss
C14: Others
C15: Tax effect of items constituting deferred tax liability
A17: AS 22.31 | C17: Tax effect of items constituting deferred tax assets
C18: Provision for compensated absences, gratuity and other employee benefits
C19: Provision for doubtful debts / advances
C20: Disallowances under Section 40(a)(i), 43B of the Income Tax Act, 1961
C21: On difference between book balance and tax balance of fixed assets
C22: Unabsorbed depreciation carried forward
C23: Brought forward business losses
C24: On items included in Reserves and surplus pending amortisation into the Statement of Profit and Loss
C25: Others
C26: Tax effect of items constituting deferred tax assets
C29: Net deferred tax (liability) / asset
A31: AS 22.32 | C31: The Company has recognised deferred tax asset on unabsorbed depreciation to the extent of the corresponding deferred tax liability on the difference between the book balance and the written down value of fixed assets under Income Tax (or) The Company has recognised deferred tax asset on unabsorbed depreciation and brought forward business losses based on the Management's estimates of future profits considering the non-cancellable customer orders received by the Company.
A32: i | C32: The net deferred tax liability / asset should always be classified as non-current and disclosed on the face of the Balance Sheet.

Sheet 30.11 AS 24 Disclosures 
B2: Name of the Company
B3: Notes forming part of the financial statements
A5: GN 6.13 | B5: Note 30 Disclosures under Accounting Standards (contd.)
A7: Ref. No. | B7: Note | C7: Particulars
A9: AS 24 | B9: 30.11 | C9: Discontinuing operations
A10: AS 24.20 | C10: During the year, pursuant to the approval of the Shareholders and other authorities as required, the Company has transferred the ________ business to _______________ on a slump sale basis with effect from the close of business on _____________ for a consideration of `______________. The ____ business was reported as part of _____ segment of the Company. The results of the discontinued business during the year until discontinuation were as under:
C12: Profit / (Loss) from ordinary activities | D12: For the year ended 31 March, 20X2 | E12: For the year ended 31 March, 20X1
D13: ` | E13: `
C14: Sale of products
C15: Sale of services
C16: Other operating revenue
A17: AS 24.20.f | C17: Total revenue (A)
A19: AS 24.20.f | C19: Cost of materials consumed
C20: Purchases of stock-in-trade
C21: Changes in inventories of finished goods, work-in-progress and stock-in-trade
C22: Employee benefits expense
C23: Finance costs
C24: Depreciation and amortisation expense
C25: Other expenses
C26: Total expenses (B)
A28: AS 24.20.g | C28: Profit / (Loss) before tax from ordinary activities (A-B)
A29: AS 24.23.a | C29: Add / (Less): Gain / (Loss) on disposal of assets / settlement of liabilities attributable to the discontinuing operation
C31: Tax expense
A32: AS 24.20.g | C32: - on ordinary activities attributable to the discontinuing operations
A33: AS 24.23.a | C33: - on gain / loss on disposal of assets / settlement of liabilities
C38: Profit / (Loss) after tax of discontinuing operations
D40: As at 31 March, 20X2 | E40: As at 31 March, 20X1
D41: ` | E41: `
A42: AS 24.20.e | C42: Carrying amount of assets as at the Balance Sheet date relating to the discontinued business to be disposed off
A43: AS 24.20.e | C43: Carrying amount of liabilities as at the Balance Sheet date relating to the discontinued business to be settled
D45: For the year ended 31 March, 20X2 | E45: For the year ended 31 March, 20X1
D46: ` | E46: `
A47: AS 24.20.h | C47: Net cash flow attributable to the discontinued business
C48: Cash flows from operating activities
C49: Cash flows from investing activities
C50: Cash flows from financing activities

Sheet 30.12 AS 26 Disclosures 
B2: Name of the Company
B3: Notes forming part of the financial statements
A5: GN 6.13 | B5: Note 30 Disclosures under Accounting Standards (contd.)
A7: Ref. No. | B7: Note | C7: Particulars | D7: For the year ended 31 March, 20X2 | E7: For the year ended 31 March, 20X1
D8: ` | E8: `
A9: AS 26 AS 26.96 | B9: 30.12 | C9: Details of research and development expenditure recognised as an expense
C10: Materials
C11: Employee benefits expense
C12: Professional fees
C13: Consumables
C14: Interest
C15: Travelling expenses
C16: Rent
C17: Depreciation
C18: Others
C20: Total

Sheet 30.13 AS 27 Disclosures
B2: Name of the Company
B3: Notes forming part of the financial statements
A5: GN 6.13 | B5: Note 30 Disclosures under Accounting Standards (contd.)
A7: Ref. No. | B7: Note | E7: Particulars
A9: AS 27 | B9: 30.13 | C9: Interest in joint ventures
C10: The Company has interests in the following jointly controlled entities:
I11: `
A12: AS 27.50 | C12: Name of companies and country of incorporation | D12: % of shareholding | E12: Amount of interest based on accounts for the year ended 31 March, 20X2
A13: AS 27.51 AS 27.52 AS 27.53 | E13: Assets | F13: Liabilities | G13: Income | H13: Expenditure | I13: Contingent liabilities | J13: Capital commitments
C14: A Ltd. , India (audited) | D14: YY | E14: YYY | F14: YYY | G14: YYY | H14: YYY | I14: YYY | J14: YYY
D15: (XX) | E15: (XXX) | F15: (XXX) | G15: (XXX) | H15: (XXX) | I15: (XXX) | J15: (XXX)
C16: B Ltd. USA (unaudited) | D16: YY | E16: YYY | F16: YYY | G16: YYY | H16: YYY | I16: YYY | J16: YYY
D17: (XX) | E17: (XXX) | F17: (XXX) | G17: (XXX) | H17: (XXX) | I17: (XXX) | J17: (XXX)
C18: Note: Figures in brackets relate to the previous year

Sheet 30.14 AS 29 Disclosures
B2: Name of the Company
B3: Notes forming part of the financial statements
A5: GN 6.13 | B5: Note 30 Disclosures under Accounting Standards (contd.)
A7: Ref. No. | B7: Note | D7: Particulars
A9: AS 29 | B9: 30.14 | C9: Details of provisions
A10: PL 5(v)(a) PL 5(v)(b) AS 29.66 GN 10.11 | C10: The Company has made provision for various contractual obligations and disputed liabilities based on its assessment of the amount it estimates to incur to meet such obligations, details of which are given below:
C11: Particulars | D11: As at 1 April, 20X1 | E11: Additions | F11: Utilisation | G11: Reversal (withdrawn as no longer required) | H11: As at 31 March, 20X2
D12: ` | E12: ` | F12: ` | G12: ` | H12: `
C13: Provision for warranty | D13: XXX | E13: XXX | F13: XXX | G13: XXX | H13: XXX
D14: (XXX) | E14: (XXX) | F14: (XXX) | G14: (XXX) | H14: (XXX)
C16: Provision for estimated losses on onerous contracts | D16: XXX | E16: XXX | F16: XXX | G16: XXX | H16: XXX
D17: (XXX) | E17: (XXX) | F17: (XXX) | G17: (XXX) | H17: (XXX)
C19: Provision for other contingencies (give details) | D19: XXX | E19: XXX | F19: XXX | G19: XXX | H19: XXX
D20: (XXX) | E20: (XXX) | F20: (XXX) | G20: (XXX) | H20: (XXX)
C22: Total | D22: XXX | E22: XXX | F22: XXX | G22: XXX | H22: XXX
D23: (XXX) | E23: (XXX) | F23: (XXX) | G23: (XXX) | H23: (XXX)
C24: Note: - Figures in brackets relate to the previous year.
C26: Of the above, the following amounts are expected to be incurred within a year:
A27: AS 29.67 | C27: Particulars | D27: As at 31 March, 20X2 | E27: As at 31 March, 20X1
D28: ` | E28: `
C29: Provision for warranty | D29: YYY | E29: YYY
C31: Provision for estimated losses on onerous contracts | D31: YYY | E31: YYY
C33: Provision for other contingencies (give details) | D33: YYY | E33: YYY

Sheet 31. Details of ESOP
B2: Name of the Company
B3: Notes forming part of the financial statements
A5: GN 6.13 | B5: Note 31 Disclosures on Employee share based payments
A7: Ref. No. | B7: Note | C7: Particulars
B8: 31 | C8: Employee Stock Option Scheme
A10: Gn 50(a) | B10: a) | C10: In the extraordinary general meeting held on ____, the shareholders approved the issue of ________ options under the Scheme titled “_________ ESOP ____” (ESOP A).
C11: The ESOP A allows the issue of options to employees of the Company and its subsidiaries (whether in India or abroad). Each option comprises one underlying equity share.
C12: As per the Scheme, the Remuneration / Compensation Committee grants the options to the employees deemed eligible. The exercise price of each option shall not be less than 85 per cent of the “Market Price” as defined in the Scheme. The options granted vest over a period of __ years from the date of the grant in proportions specified in the Scheme. Options may be exercised within __ days of vesting.
A13: Gn 48 | C13: The difference between the fair price of the share underlying the options granted on the date of grant of option and the exercise price of the option (being the intrinsic value of the option) representing Stock compensation expense is expensed over the vesting period.
A15: Gn 50(a) | B15: b) | C15: The ESOP scheme titled “_____ ESOP ___” (ESOP B) was approved by the shareholders through postal ballot on __________. ______ options are covered under the scheme for __________shares.
C16: In the previous years, the Remuneration / Compensation Committee of the Company had granted ________ options under the ESOP B to few eligible employees of the Company. During the current year, the Remuneration / Compensation Committee in its meeting held on _____, _____ and _____ has granted _________, ________ and ________ options respectively under the ESOP B to few eligible employees of the Company. The options allotted under ESOP B are convertible into equal number of equity shares.
C17: The vesting period of these options range over a period of ___ years. The options may be exercised with in a period of ___ days from the date of vesting.
A19: Gn 50(a) | B19: c) | C19: The ESOP scheme titled “_____ ESOP ___ (Directors)” [ESOP (Directors)] was approved by the shareholders through postal ballot on _____. _________ options are covered under the scheme for _________ equity shares.
C20: The Remuneration / Compensation Committee of the Company, had granted ________ options under this scheme to few Directors of the Company. The shares covered by such options were ________ equity shares.
C21: The vesting period of these options range over a period of ____ years. The options may be exercised with in a period of ___ days from the date of vesting.
A23: Gn 50(b) | B23: d) | C23: Employee stock options details as on the Balance Sheet date are as follows:
C25: Particulars | D25: During the year ended 31 March, 20X2 | F25: During the year ended 31 March, 20X1
D26: Options (Numbers) | E26: Weighted average exercise price per option (`) | F26: Options (Numbers) | G26: Weighted average exercise price per option (`)
C27: Option outstanding at the beginning of the year:
C28: - ESOP A
C29: - ESOP B
C30: - ESOP (Director)
C31: Granted during the year:
C32: - ESOP A
C33: - ESOP B
C34: - ESOP (Director)
C35: Vested during the year:
C36: - ESOP A
C37: - ESOP B
C38: - ESOP (Director)
... C54: - ESOP (Director)
A56: GN 6.13 | C56: Note 31 Disclosures on Employee share based payments (contd.)
A58: Ref. No. | B58: Note | C58: Particulars
B59: e) | C59: The impact on Earnings per Share if the ‘fair value’ of the options (on the date of the grant) were considered instead of the ‘intrinsic value’ is as under:
C60: Particulars | D60: For the year ended 31 March, 20X2 | E60: For the year ended 31 March, 20X1
D61: ` | E61: `
C62: Net Profit / (loss) (as reported)
C63: Add / (Less): stock based employee compensation (intrinsic value)
C64: Add / (Less): stock based compensation expenses determined under fair value method for the grants issued (See note (f) below)
C65: Net Profit / (loss) (proforma)
C67: Basic earnings per share (as reported)
A68: Gn 48 | C68: Basic earnings per share (proforma)
C69: Diluted earnings per share (as reported)
A70: Gn 48 | C70: Diluted earnings per share (proforma)
A72: Gn 51 | B72: f) | C72: The fair value of the options has been determined under the Black-Scholes model. The assumptions used in this model for calculating fair value are as below:
C74: Assumptions | D74: 31 March, 20X2 | E74: 31 March, 20X1
C75: Risk Free Interest Rate
C76: Expected Life
C77: Expected Annual Volatility of Shares
C78: Expected Dividend Yield

Sheet 32. Previous Year's Figures
B2: Name of the Company
B3: Notes forming part of the financial statements
B5: Note 32 Previous year's figures
A6: Ref No. | B6: Note | C6: Particulars
B7: 32 | C7: The Revised Schedule VI has become effective from 1 April, 2011 for the preparation of financial statements. This has significantly impacted the disclosure and presentation made in the financial statements. Previous year's figures have been regrouped / reclassified wherever necessary to correspond with the current year's classification / disclosure.
A8: i | C8: The Revised Schedule VI does not require presentation of a reconciliation explaining the impact of the reclassification of the previous year figures in the financial statements. However, the company may consider giving an appropriate reconciliation in the Notes as an additional information as it would help in clarifying the impact of the reclassification of the previous year figures.

Sheet Note 6A Fixed Assets Own Funds
B1: SGBS UNNATI FOUNDATION
B2: Notes forming part of the financial statements
B6: 6A | C6: FIXED ASSETS: OWN FUNDS 2015-16
B7: Sl No. | C7: Description | D7: W.D.V.As on | E7: Additions | G7: Deletions | H7: Total | I7: Depreciation | K7: W.D.V. As on
D8: 01.04.2015 | E8: 1st half | F8: 2nd half | I8: Rate | J8: Total | K8: 31.03.2016
B10: 1 | C10: Computers | D10: ='Master FA 2014-15 revised'!K22 -> 562431 | E10: 411804 | F10: 10023 | G10: 0 | H10: =(D10+E10+F10)-G10 -> 984258 | J10: 783262 | K10: =H10-J10 -> 200996
B11: 2 | C11: Furniture & Fixtures | D11: ='Master FA 2014-15 revised'!K23 -> 448616 | E11: 1750 | F11: 0 | G11: 0 | H11: =(D11+E11+F11)-G11 -> 450366 | J11: 182877 | K11: =H11-J11 -> 267489
B12: 3 | C12: Land | D12: ='Master FA 2014-15 revised'!K24 -> 3500640 | E12: 0 | F12: 0 | G12: 0 | H12: =(D12+E12+F12)-G12 -> 3500640 | J12: 0 | K12: =H12-J12 -> 3500640
B13: 4 | C13: Office Equipment | D13: ='Master FA 2014-15 revised'!K25 -> 158110.45 | E13: 45780 | F13: 99402 | G13: 1469 | H13: =(D13+E13+F13)-G13 -> 301823.45 | J13: 161697 | K13: =H13-J13 -> 140126.45
H14: =(D14+E14+F14)-G14 -> 0 | J14: =ROUND(((D14+E14)*I14)+(F14*I14/2),0) -> 0 | K14: =H14-J14 -> 0
H15: =(D15+E15+F15)-G15 -> 0 | J15: =ROUND(((D15+E15)*I15)+(F15*I15/2),0) -> 0 | K15: =H15-J15 -> 0
H16: =(D16+E16+F16)-G16 -> 0 | J16: =ROUND(((D16+E16)*I16)+(F16*I16/2),0) -> 0 | K16: =H16-J16 -> 0
C17: Grand Total | D17: =SUM(D9:D16) -> 4669797.5 | E17: =SUM(E9:E16) -> 459334 | F17: =SUM(F9:F16) -> 109425 | G17: =SUM(G9:G16) -> 1469 | H17: =SUM(H9:H16) -> 5237087.5 | J17: =SUM(J9:J16) -> 1127836 | K17: =SUM(K9:K16) -> 4109251.5

Sheet Master Fixed Assets 2015-16
B1: SGBS UNNATI FOUNDATION
B2: Notes forming part of the financial statements
B5: Note:6 | C5: FIXED ASSETS: GROSS 2015-16
B6: Sl No. | C6: Description | D6: W.D.V.As on | E6: Additions | G6: Deletions | H6: Total | I6: Depreciation | K6: W.D.V. As on
D7: 01.04.2015 | E7: 1st half | F7: 2nd half | I7: Rate | J7: Total | K7: 31.03.2016
B9: 1 | C9: Computers | D9: 842085 | E9: 1794638 | F9: 2283966 | G9: 23871 | H9: =(D9+E9+F9)-G9 -> 4896818 | J9: 3492028.7 | K9: =H9-J9 -> 1404789.3
B10: 2 | C10: Furniture & Fixtures | D10: 712422 | E10: 390667 | F10: 472326 | G10: 123971 | H10: =(D10+E10+F10)-G10 -> 1451444 | J10: 509961.07 | K10: =H10-J10 -> 941482.93
B11: 3 | C11: Land | D11: 3500640 | E11: 0 | F11: 0 | G11: 0 | H11: =(D11+E11+F11)-G11 -> 3500640 | J11: 0 | K11: =H11-J11 -> 3500640
B12: 4 | C12: Office Equipment | D12: 354605.45 | E12: 942708 | F12: 1469803 | G12: 69780 | H12: =(D12+E12+F12)-G12 -> 2697336.5 | J12: 1323168 | K12: =H12-J12 -> 1374168.4
H13: =(D13+E13+F13)-G13 -> 0 | J13: =ROUND(((D13+E13)*I13)+(F13*I13/2),0) -> 0 | K13: =H13-J13 -> 0
H14: =(D14+E14+F14)-G14 -> 0 | J14: =ROUND(((D14+E14)*I14)+(F14*I14/2),0) -> 0 | K14: =H14-J14 -> 0
H15: =(D15+E15+F15)-G15 -> 0 | J15: =ROUND(((D15+E15)*I15)+(F15*I15/2),0) -> 0 | K15: =H15-J15 -> 0
C16: Grand Total | D16: =SUM(D8:D15) -> 5409752.5 | E16: =SUM(E8:E15) -> 3128013 | F16: =SUM(F8:F15) -> 4226095 | G16: =SUM(G8:G15) -> 217622 | H16: =SUM(H8:H15) -> 12546238 | J16: =SUM(J8:J15) -> 5325157.8 | K16: =SUM(K8:K15) -> 7221080.7
C20: FIXED ASSETS: GRANT FUNDS 2015-16
B21: Sl No. | C21: Description | D21: W.D.V.As on | E21: Additions | G21: Deletions | H21: Total | I21: Depreciation | K21: W.D.V. As on
D22: 01.04.2015 | E22: 1st half | F22: 2nd half | I22: Rate | J22: Total | K22: 31.03.2016
B24: 1 | C24: Computers | D24: 0 | E24: 1370609 | F24: 2262297 | G24: 0 | H24: =(D24+E24+F24)-G24 -> 3632906 | J24: 2482861.8 | K24: =H24-J24 -> 1150044.2
B25: 2 | C25: Furniture & Fixtures | D25: 0 | E25: 313601 | F25: 423671 | G25: 0 | H25: =(D25+E25+F25)-G25 -> 737272 | J25: 235207.1 | K25: =H25-J25 -> 502064.9
B26: 3 | C26: Land | D26: 0 | E26: 0 | F26: 0 | G26: 0 | H26: =(D26+E26+F26)-G26 -> 0 | J26: 0 | K26: =H26-J26 -> 0
B27: 4 | C27: Office Equipment | D27: 0 | E27: 857680 | F27: 1341338 | G27: 0 | H27: =(D27+E27+F27)-G27 -> 2199018 | J27: 1055469.9 | K27: =H27-J27 -> 1143548.1
H28: =(D28+E28+F28)-G28 -> 0 | J28: =ROUND(((D28+E28)*I28)+(F28*I28/2),0) -> 0 | K28: =H28-J28 -> 0
H29: =(D29+E29+F29)-G29 -> 0 | J29: =ROUND(((D29+E29)*I29)+(F29*I29/2),0) -> 0 | K29: =H29-J29 -> 0
H30: =(D30+E30+F30)-G30 -> 0 | J30: =ROUND(((D30+E30)*I30)+(F30*I30/2),0) -> 0 | K30: =H30-J30 -> 0
C31: Grand Total | D31: =SUM(D23:D30) -> 0 | E31: =SUM(E23:E30) -> 2541890 | F31: =SUM(F23:F30) -> 4027306 | G31: =SUM(G23:G30) -> 0 | H31: =SUM(H23:H30) -> 6569196 | J31: =SUM(J23:J30) -> 3773538.8 | K31: =SUM(K23:K30) -> 2795657.2
C34: FIXED ASSETS: GRANT FUNDS 2014-15 - DEPRECIATION FOR FY 2015-16
B35: Sl No. | C35: Description | D35: W.D.V.As on | E35: Additions | G35: Deletions | H35: Total | I35: Depreciation | K35: W.D.V. As on
D36: 01.04.2015 | E36: 1st half | F36: 2nd half | I36: Rate | J36: Total | K36: 31.03.2016
B38: 1 | C38: Computers | D38: ='Master FA 2014-15 revised'!K8 -> 279654 | G38: 0 | H38: =(D38+E38+F38)-G38 -> 279654 | J38: 225905 | K38: =H38-J38 -> 53749
B39: 2 | C39: Furniture & Fixtures | D39: ='Master FA 2014-15 revised'!K9 -> 263806 | G39: 0 | H39: =(D39+E39+F39)-G39 -> 263806 | J39: 91877 | K39: =H39-J39 -> 171929
B40: 3 | C40: Land | D40: 0 | G40: 0 | H40: =(D40+E40+F40)-G40 -> 0 | J40: 0 | K40: =H40-J40 -> 0
B41: 4 | C41: Office Equipment | D41: ='Master FA 2014-15 revised'!K11 -> 196495 | G41: 0 | H41: =(D41+E41+F41)-G41 -> 196495 | J41: 106001 | K41: =H41-J41 -> 90494
H42: =(D42+E42+F42)-G42 -> 0 | J42: =ROUND(((D42+E42)*I42)+(F42*I42/2),0) -> 0 | K42: =H42-J42 -> 0
H43: =(D43+E43+F43)-G43 -> 0 | J43: =ROUND(((D43+E43)*I43)+(F43*I43/2),0) -> 0 | K43: =H43-J43 -> 0
H44: =(D44+E44+F44)-G44 -> 0 | J44: =ROUND(((D44+E44)*I44)+(F44*I44/2),0) -> 0 | K44: =H44-J44 -> 0
C45: Grand Total | D45: =SUM(D37:D44) -> 739955 | E45: =SUM(E37:E44) -> 0 | F45: =SUM(F37:F44) -> 0 | G45: =SUM(G37:G44) -> 0 | H45: =SUM(H37:H44) -> 739955 | J45: =SUM(J37:J44) -> 423783 | K45: =SUM(K37:K44) -> 316172
C49: FIXED ASSETS: OWN FUNDS 2015-16
B50: Sl No. | C50: Description | D50: W.D.V.As on | E50: Additions | G50: Deletions | H50: Total | I50: Depreciation | K50: W.D.V. As on
D51: 01.04.2015 | E51: 1st half | F51: 2nd half | I51: Rate | J51: Total | K51: 31.03.2016
B53: 1 | C53: Computers | D53: ='Master FA 2014-15 revised'!K22 -> 562431 | E53: 411804 | F53: 10023 | G53: 0 | H53: =(D53+E53+F53)-G53 -> 984258 | J53: 783262 | K53: =H53-J53 -> 200996
B54: 2 | C54: Furniture & Fixtures | D54: ='Master FA 2014-15 revised'!K23 -> 448616 | E54: 1750 | F54: 0 | G54: 0 | H54: =(D54+E54+F54)-G54 -> 450366 | J54: 182877 | K54: =H54-J54 -> 267489
B55: 3 | C55: Land | D55: ='Master FA 2014-15 revised'!K24 -> 3500640 | E55: 0 | F55: 0 | G55: 0 | H55: =(D55+E55+F55)-G55 -> 3500640 | J55: 0 | K55: =H55-J55 -> 3500640
B56: 4 | C56: Office Equipment | D56: ='Master FA 2014-15 revised'!K25 -> 158110.45 | E56: 45780 | F56: 99402 | G56: 1469 | H56: =(D56+E56+F56)-G56 -> 301823.45 | J56: 161697 | K56: =H56-J56 -> 140126.45
H57: =(D57+E57+F57)-G57 -> 0 | J57: =ROUND(((D57+E57)*I57)+(F57*I57/2),0) -> 0 | K57: =H57-J57 -> 0
H58: =(D58+E58+F58)-G58 -> 0 | J58: =ROUND(((D58+E58)*I58)+(F58*I58/2),0) -> 0 | K58: =H58-J58 -> 0
H59: =(D59+E59+F59)-G59 -> 0 | J59: =ROUND(((D59+E59)*I59)+(F59*I59/2),0) -> 0 | K59: =H59-J59 -> 0
C60: Grand Total | D60: =SUM(D52:D59) -> 4669797.5 | E60: =SUM(E52:E59) -> 459334 | F60: =SUM(F52:F59) -> 109425 | G60: =SUM(G52:G59) -> 1469 | H60: =SUM(H52:H59) -> 5237087.5 | J60: =SUM(J52:J59) -> 1127836 | K60: =SUM(K52:K59) -> 4109251.5
C62: TOTAL FIXED ASSETS 2015-16 | D62: =D60+D45+D31 -> 5409752.5 | E62: =E60+E45+E31 -> 3001224 | F62: =F60+F45+F31 -> 4136731 | G62: =G60+G45+G31 -> 1469 | H62: =H60+H45+H31 -> 12546238 | I62: =I60+I45+I31 -> 0 | J62: =J60+J45+J31 -> 5325157.8 | K62: =K60+K45+K31 -> 7221080.7
J64: =+J60 -> 1127836 | K64: deprn in I&E
J65: =+J45+J31 -> 4197321.8 | K65: deprn to Asset Reserve
J66: =+J65+J64 -> 5325157.8

Sheet Master FA 2014-15 revised
B1: SGBS UNNATI FOUNDATION
B2: Notes forming part of the financial statements
B4: Note 6A | C4: FIXED ASSETS: GRANT FUNDS 2014-15
B5: Sl No. | C5: Description | D5: W.D.V.As on | E5: Additions | G5: Deletions | H5: Total | I5: Depreciation | K5: W.D.V. As on
D6: 01.04.2015 | E6: 1st half | F6: 2nd half | I6: Rate | J6: Total | K6: 31.03.2016
B8: 1 | C8: Computers | D8: 0 | E8: 0 | F8: 809639 | G8: 0 | H8: =(D8+E8+F8)-G8 -> 809639 | J8: 529985 | K8: =H8-J8 -> 279654
B9: 2 | C9: Furniture & Fixtures | D9: 0 | E9: 0 | F9: 383816 | G9: 0 | H9: =(D9+E9+F9)-G9 -> 383816 | J9: 120010 | K9: =H9-J9 -> 263806
B10: 3 | C10: Land | D10: 0 | E10: 0 | F10: 0 | G10: 0 | H10: =(D10+E10+F10)-G10 -> 0 | J10: 0 | K10: =H10-J10 -> 0
B11: 4 | C11: Office Equipment | D11: 0 | E11: 0 | F11: 363686 | G11: 0 | H11: =(D11+E11+F11)-G11 -> 363686 | J11: 167191 | K11: =H11-J11 -> 196495
H12: =(D12+E12+F12)-G12 -> 0 | J12: =ROUND(((D12+E12)*I12)+(F12*I12/2),0) -> 0 | K12: =H12-J12 -> 0
H13: =(D13+E13+F13)-G13 -> 0 | J13: =ROUND(((D13+E13)*I13)+(F13*I13/2),0) -> 0 | K13: =H13-J13 -> 0
H14: =(D14+E14+F14)-G14 -> 0 | J14: =ROUND(((D14+E14)*I14)+(F14*I14/2),0) -> 0 | K14: =H14-J14 -> 0
C15: Grand Total | D15: =SUM(D7:D14) -> 0 | E15: =SUM(E7:E14) -> 0 | F15: =SUM(F7:F14) -> 1557141 | G15: =SUM(G7:G14) -> 0 | H15: =SUM(H7:H14) -> 1557141 | J15: =SUM(J7:J14) -> 817186 | K15: =SUM(K7:K14) -> 739955
C18: FIXED ASSETS: OWN FUNDS 2014-15
B19: Sl No. | C19: Description | D19: W.D.V.As on | E19: Additions | G19: Deletions | H19: Total | I19: Depreciation | K19: W.D.V. As on
D20: 01.04.2015 | E20: 1st half | F20: 2nd half | I20: Rate | J20: Total | K20: 31.03.2016
B22: 1 | C22: Computers | D22: 622254 | E22: 1700 | F22: 1280396 | G22: 0 | H22: =(D22+E22+F22)-G22 -> 1904350 | J22: 1341919 | K22: =H22-J22 -> 562431
B23: 2 | C23: Furniture & Fixtures | D23: 577586 | E23: 0 | F23: 123293 | G23: 0 | H23: =(D23+E23+F23)-G23 -> 700879 | J23: 252263 | K23: =H23-J23 -> 448616
B24: 3 | C24: Land | D24: 3500640 | E24: 0 | F24: 0 | G24: 0 | H24: =(D24+E24+F24)-G24 -> 3500640 | J24: 0 | K24: =H24-J24 -> 3500640
B25: 4 | C25: Office Equipment | D25: 127188.45 | E25: 5690 | F25: 186892 | G25: 0 | H25: =(D25+E25+F25)-G25 -> 319770.45 | J25: 161660 | K25: =H25-J25 -> 158110.45
H26: =(D26+E26+F26)-G26 -> 0 | J26: =ROUND(((D26+E26)*I26)+(F26*I26/2),0) -> 0 | K26: =H26-J26 -> 0
H27: =(D27+E27+F27)-G27 -> 0 | J27: =ROUND(((D27+E27)*I27)+(F27*I27/2),0) -> 0 | K27: =H27-J27 -> 0
H28: =(D28+E28+F28)-G28 -> 0 | J28: =ROUND(((D28+E28)*I28)+(F28*I28/2),0) -> 0 | K28: =H28-J28 -> 0
C29: Grand Total | D29: =SUM(D21:D28) -> 4827668.5 | E29: =SUM(E21:E28) -> 7390 | F29: =SUM(F21:F28) -> 1590581 | G29: =SUM(G21:G28) -> 0 | H29: =SUM(H21:H28) -> 6425639.5 | J29: =SUM(J21:J28) -> 1755842 | K29: =SUM(K21:K28) -> 4669797.5
B31: TOTAL FIXED ASSETS 2014-15 | D31: =D29+D15 -> 4827668.5 | E31: =E29+E15 -> 7390 | F31: =F29+F15 -> 3147722 | G31: =G29+G15 -> 0 | H31: =H29+H15 -> 7982780.5 | I31: =I29+I15 -> 0 | J31: =J29+J15 -> 2573028 | K31: =K29+K15 -> 5409752.5
J33: =+J29 -> 1755842 | K33: to show in last year I &E (reclassfied)
J34: =+J15 -> 817186 | K34: to charge to Asset Reserve
J35: =+J34+J33 -> 2573028 | K35: as shown in I&E of 2014 2015

Sheet Depn details
A1: FA Particulars | B1: FY 2014-15 | C1: FY 2015-16 local | D1: FY 2015-16 fcra
A2: Grant
A3: Comp | B3: 528408 | C3: 2517244 | D3: 57660
A4: Printer | C4: 129844 | D4: 3337
A5: S/w | B5: 1577 | C5: 681
A6: Total Comp | B6: =SUM(B3:B5) -> 529985 | C6: =SUM(C3:C5) -> 2647769 | D6: =SUM(D3:D5) -> 60997
A7: FF
A8: Almirah | B8: 5331 | C8: 17983 | D8: 609
A9: Board | B9: 16723 | C9: 12740
A10: Chairs | B10: 34742 | C10: 112415 | D10: 2792
A11: Fan | B11: 5379 | C11: 13017 | D11: 190
A12: Light | B12: 231 | C12: 175
A13: Off infr | B13: 37290 | C13: 108446 | D13: 2405
A14: Tables | B14: 20315 | C14: 54946 | D14: 1366
A16: Total FF | B16: =SUM(B8:B15) -> 120011 | C16: =SUM(C8:C15) -> 319722 | D16: =SUM(D8:D15) -> 7362
A18: Biometric | C18: 226872 | D18: 4340
A19: Recorder | B19: 1990 | C19: 1279
A20: Router | B20: 59185 | C20: 428974 | D20: 12554
A21: Stabiliser | B21: 1169 | C21: 732
A22: Teleph | B22: 2269 | C22: 1451
A23: Tv | B23: 58384 | C23: 230327 | D23: 3014
A24: usb
A25: ups | B25: 44193 | C25: 247524 | D25: 4405
A26: Total OE | B26: =SUM(B18:B25) -> 167190 | C26: =SUM(C18:C25) -> 1137159 | D26: =SUM(D18:D25) -> 24313
A27: Total Grant | B27: =B26+B16+B6 -> 817186 | C27: =C26+C16+C6 -> 4104650 | D27: =D26+D16+D6 -> 92672
A28: SUF
A29: Comp | B29: =1205316-B30 -> 1197398 | C29: 436645
A30: Printer | B30: 7918 | C30: 21714
A31: S/w | B31: 136602.93 | C31: 324903
A32: Total Comp | B32: =SUM(B29:B31) -> 1341918.9 | C32: =SUM(C29:C31) -> 783262 | D32: =SUM(D29:D31) -> 0
A33: FF
A34: Almirah | C34: 2661
A35: Board | C35: 1951
A36: Chairs | C36: 38902
A37: Fan | C37: 1517
A38: Light | C38: 2973
A39: Off infr | C39: 86985
A40: Tables | C40: 39531
A42: Total FF | B42: 252263 | C42: =SUM(C34:C41) -> 174520 | D42: =SUM(D34:D41) -> 0
A44: Air con | C44: 8358
A45: Biometric | C45: 22504
A46: Camera | B46: 11034.86 | C46: 4632
A47: Coffee Maker | B47: 2081.03 | C47: 1204
A48: Recorder | B48: 5420.36 | C48: 3484
A49: Router | B49: 59185.1 | C49: 38767
A50: Stabiliser
A51: Teleph | B51: 5386.36 | C51: 3345
A52: Tv | B52: 77694.17 | C52: 61982
A53: usb
A54: ups | B54: 857.91 | C54: 493
A55: Water Cooler | C55: 25285
A56: Total OE | B56: =SUM(B44:B55) -> 161659.79 | C56: =SUM(C44:C55) -> 170054 | D56: =SUM(D44:D55) -> 0
A58: Total Depn | B58: =B56+B42+B32+B26+B16+B6 -> 2573027.7 | C58: =C56+C42+C32+C26+C16+C6 -> 5232486 | D58: =D56+D42+D32+D26+D16+D6 -> 92672
C59: =4197322+1127836 -> 5325158 | D59: =C58+D58 -> 5325158
A60: Depn Revd | B60: =817186+1755842 -> 2573028 | C60: =1127836+4104650 -> 5232486 | D60: 92672
A62: trfd to def grant | C62: =3680866 -> 3680866 | D62: 92672
C63: 423783
A65: def grant revd | C65: 3680867 | D65: 92672
C66: 423783
A70: gen fund - FA | B70: 1557141
A71: gen fund - depn | B71: 817186

Sheet Yearly comparison
A1: Particulars | B1: 2019-2020 | C1: 2018-2019 | D1: 2017-2018
A2: Donations & Grants | B2: ='Income & Expenditure'!D10 -> 0 | C2: 60740448 | D2: 40566086
A3: Fees | B3: ='Notes 2 to 11'!#REF!+'Notes 2 to 11'!#REF! -> #REF! | C3: ='Notes 2 to 11'!#REF!+'Notes 2 to 11'!#REF! -> #REF! | D3: 3675082
A4: Interest Income | B4: ='Notes 2 to 11'!B81 -> #REF! | C4: ='Notes 2 to 11'!C81+'Notes 2 to 11'!C82 -> 12151770 | D4: 675094
A5: Other Income | B5: ='Notes 2 to 11'!B83 -> #REF! | C5: ='Notes 2 to 11'!C83 -> 374883 | D5: 25009
A6: Total Income | B6: =SUM(B2:B5) -> #REF! | C6: =SUM(C2:C5) -> #REF! | D6: =SUM(D2:D5) -> 44941271
A8: Operations Expenses
A9: Salary | B9: ='Income & Expenditure'!D15 -> 0 | C9: 29018195 | D9: 32212137
A10: Advertisement & Publicity | B10: ='Notes 2 to 11'!B112 -> #REF! | C10: 980398.93 | D10: 873994.79
A11: Audit Fee | B11: ='Notes 2 to 11'!B126 -> 0 | C11: 29500 | D11: 25000
A12: Bank Charges | B12: ='Notes 2 to 11'!B101 -> #REF! | C12: 10275.44 | D12: 5956.61
A13: Centre Setup & Shifting Expenses | B13: ='Notes 2 to 11'!B103 -> #REF! | C13: 162964 | D13: 0
A14: Computer Maintenance | B14: ='Notes 2 to 11'!B104 -> #REF! | C14: 174491.59 | D14: 139373
A15: Consultancy Charges for Technical Training | B15: ='Notes 2 to 11'!#REF! -> #REF! | C15: 1016934 | D15: 0 | E15: portea
A16: Depreciation | B16: ='Notes 2 to 11'!#REF! -> #REF! | C16: 407607 | D16: 694587
A17: Electricity & Water | B17: ='Notes 2 to 11'!B105 -> #REF! | C17: 216676.51 | D17: 199298.63
A18: IBM Program Expenses | B18: ='Notes 2 to 11'!#REF! -> #REF! | C18: 6195425.7 | D18: 0
A19: Infrastructure Purchases From Restricted Funds | B19: ='Notes 2 to 11'!B100 -> #REF! | C19: 904975 | D19: 951798
A20: Loss on sale / discarding of asset | B20: ='Notes 2 to 11'!B131 -> #REF! | C20: 59170.8 | D20: 174790.3
A21: Miscelleneous Expenses | B21: ='Notes 2 to 11'!B132 -> 0 | C21: 889 | D21: 4084
A22: Playablo Expenses | B22: ='Notes 2 to 11'!#REF! -> #REF! | C22: 1335306 | D22: 0
A23: Postage & Telephone | B23: ='Notes 2 to 11'!B113 -> #REF! | C23: 648900.87 | D23: 764984.91
A24: Printing and stationery | B24: ='Notes 2 to 11'!B114 -> #REF! | C24: 113251.96 | D24: 213027.53
A25: Professional Charges | B25: ='Notes 2 to 11'!#REF! -> #REF! | C25: 136660 | D25: 61000
A26: Rates & Taxes | B26: 32561.33 | C26: 14126 | D26: 9630.9
A27: Rent | B27: ='Notes 2 to 11'!B115 -> #REF! | C27: 2207762 | D27: 2120550
A28: Repairs & Maintenance | B28: ='Notes 2 to 11'!B106 -> #REF! | C28: 1124545 | D28: 519542.36
A29: Recruitment Expenses | B29: ='Notes 2 to 11'!#REF! -> #REF! | C29: 122042.56 | D29: 0
A30: Software Subscription | B30: ='Notes 2 to 11'!B116 -> #REF! | C30: 1239212.4 | D30: 1217226.6
A31: Staff Training Expenses | B31: ='Notes 2 to 11'!B117 -> #REF! | C31: 3644435 | D31: 1215495
A32: Staff Welfare | B32: ='Notes 2 to 11'!B118 -> #REF! | C32: 204959 | D32: 217663
A33: Students Training Expenses | B33: ='Notes 2 to 11'!#REF! -> #REF! | C33: 678841.72 | D33: 913088
A34: Sundry Balances w/off | B34: ='Notes 2 to 11'!B136 -> #REF! | C34: 61536.82 | D34: 35971.42
A35: Social Service Project Expenses | B35: ='Notes 2 to 11'!#REF! -> #REF! | C35: 3097500 | D35: 0
A36: Travelling and conveyance | B36: ='Notes 2 to 11'!B121 -> #REF! | C36: 1718792.8 | D36: 1068177
A38: Total Expenses | B38: =SUM(B9:B37) -> #REF! | C38: =SUM(C9:C37) -> 55525375 | D38: =SUM(D9:D37) -> 43637376
A39: Total Surplus | B39: =B6-B38 -> #REF! | C39: =C6-C38 -> #REF! | D39: =D6-D38 -> 1303895
A41: No of youth - Unnati
A42: No of youth - UNXT
A43: No of staff | B43: 124 | C43: 130 | D43: 145

Sheet R&P crs working
A1: SUF GROUP 2019 2020
A2: SUNDRY CREDITORS
A3: Group Summary
A4: 1-Apr-2019 to 31-Mar-2020
B5: SUNDRY CREDITORS
B6: SUF GROUP 2019 2020
A7: Particulars | B7: 1-Apr-2019 to 31-Mar-2020
B8: Transactions
B9: Receipts | C9: Payments | D9: FA | E9: Exps
A10: EZON ENERGY SOLUTION PVT LTD | C10: 1700000
A11: FEATHERLITE PRODUCTS PVT LTD | C11: 139092
A12: GALAXY POWER SYSTEMS (CHIDAMBARAM) | C12: 28000
A13: GAYATHRI ENTERPRISES | C13: 103949
A14: JAI MEENAKSHI FURNITURE (MADURAI) | C14: 5200
A15: JAYA TRADING COMPANY ( MADURAI) | C15: 28500
A16: M/S DOVETAIL FURNITURE PVT LTD (BANGALORE - HO) | C16: 295403
A17: NANDHA KUMAR(SELVAM CHIDAMBARAM) | C17: 203079
A18: NEW FIVE STAR AGENCY (DINDIGUL) | C18: 75800
A19: NEW JOICE FURNITURE ( MADURAI) | C19: 4000
A20: NOOTHANAM (CHIDAMBARAM) | C20: 20100
A21: PANACEA INNOVATIVE TECHNOLOGIES | C21: 12300
... A35: WEATHER MAKER ( MADURAI) | C35: 46000
A36: SYSTECH SERVICES LTD | C36: 2246248.8 | D36: 1827160 | E36: =C36-D36 -> 419088.76
A37: Total FA | C37: =SUM(C10:C36) -> 5227644.8
C38: =C37-C36+D36 -> 4808556 | D38: FA for R&P
